Workbook

Sheet Apoio
B2: Centros de Custo | C2: Desc. Centro de Custo | D2: Gestor | F2: Comercialização | G2: Gestão | H2: Geração | J2: Filial | K2: Nome Reduzido | L2: Cluster
B3: C100 | C3: Diretoria | D3: Fernanda Barbosa | J3: ECEL - ELÉTRON COMERCIALIZADORA DE ENERGIA S.A. | K3: ECEL COMERCIALIZADORA | L3: COMERCIALIZADORA | M3: ECEL - ELETRON COMERCIALI
B4: C101 | C4: Comercial | D4: João Lins | J4: MERCURIA COMERCIALIZADORA DE ENERGIA DO BRASIL LTDA | K4: MERCURIA COMERCIALIZADORA | L4: COMERCIALIZADORA | M4: MERCURIA COMERCIALIZADORA
B5: C102 | C5: Jurídico | D5: Cesar Souza | J5: ELETRON POWER GERACAO E COMERCIALIZADORA DE ENERGIA S.A. | K5: ELETRON POWER GERACAO | L5: ELETRON POWER GERACAO | M5: ELETRON POWER GERACAO E C
B6: C103 | C6: Marketing | D6: Mayra Souza | J6: UFV IBIMIRIM 1 GERACAO DE ENERGIA ELETRICA LTDA | K6: UFV IBIMIRIM 1 | L6: IBIMIRINS | M6: UFV IBIMIRIM 1 GERACAO DE
B7: C104 | C7: TI | D7: Marcelo Bronzatti | J7: UFV IBIMIRIM 2 GERACAO DE ENERGIA ELETRICA LTDA | K7: UFV IBIMIRIM 2 | L7: IBIMIRINS | M7: UFV IBIMIRIM 2 GERACAO DE
B8: C105 | C8: Estrutura Corporativo | D8: Rafael Silva | J8: UFV IBIMIRIM 3 GERACAO DE ENERGIA ELETRICA LTDA | K8: UFV IBIMIRIM 3 | L8: IBIMIRINS | M8: UFV IBIMIRIM 3 GERACAO DE
B9: C106 | C9: Gente e Gestão | D9: Emanuelli Colvara | J9: UFV IBIMIRIM 4 GERACAO DE ENERGIA ELETRICA LTDA | K9: UFV IBIMIRIM 4 | L9: IBIMIRINS | M9: UFV IBIMIRIM 4 GERACAO DE
B10: C107 | C10: Tesouraria | D10: Ruan Pereira | J10: UFV IBIMIRIM 5 GERACAO DE ENERGIA ELETRICA LTDA | K10: UFV IBIMIRIM 5 | L10: IBIMIRINS | M10: UFV IBIMIRIM 5 GERACAO DE
B11: C108 | C11: Controladoria | D11: Ray Salvador | J11: UFV IBIMIRIM 6 GERACAO DE ENERGIA ELETRICA LTDA | K11: UFV IBIMIRIM 6 | L11: IBIMIRINS | M11: UFV IBIMIRIM 6 GERACAO DE
B12: C109 | C12: Fiscal | D12: Carlos Augusto Brito | J12: UFV IBIMIRIM 7 GERACAO DE ENERGIA ELETRICA LTDA | K12: UFV IBIMIRIM 7 | L12: IBIMIRINS | M12: UFV IBIMIRIM 7 GERACAO DE
B13: C121 | C13: Cobrança Ecel | D13: Ruan Pereira | J13: UFV IBIMIRIM 8 GERACAO DE ENERGIA ELETRICA LTDA | K13: UFV IBIMIRIM 8 | L13: IBIMIRINS | M13: UFV IBIMIRIM 8 GERACAO DE
B14: C200 | C14: Trading | D14: Fernanda Barbosa | J14: UFV IBIMIRIM 9 GERACAO DE ENERGIA ELETRICA LTDA | K14: UFV IBIMIRIM 9 | L14: IBIMIRINS | M14: UFV IBIMIRIM 9 GERACAO DE
... B21: C600 | C21: Recuperação Judicial (RJ) | D21: Cesar Souza | J21: NOVA RIACHO PARTICIPACOES S.A | K21: NOVA RIACHO PARTICIPACOES | L21: RIACHO | M21: NOVA RIACHO PARTICIPACOES
J22: ELETRON SERVIÇOS LTDA | K22: ELETRON SERVICOS | L22: ELETRON SERVICOS | M22: ELETRON SERVICOS LTDA
J23: ELETRON POWER GD I S.A. | K23: ELETRON POWER GD I | L23: ELETRON POWER GD I | M23: ELETRON POWER GD I S.A.
J24: SPE SE IBIMIRIM ENERGIA LTDA | K24: SPE SE IBIMIRIM | L24: IBIMIRINS | M24: SPE SE IBIMIRIM ENERGIA L
J25: UFV TAPAJOS 1 ENERGIA LTDA | K25: UFV TAPAJOS 1 | L25: GDs | M25: UFV TAPAJOS 1 ENERGIA LTD
J26: UFV TAPAJOS 2 ENERGIA LTDA | K26: UFV TAPAJOS 2 | L26: GDs | M26: UFV TAPAJOS 2 ENERGIA LTD
J27: UFV TAPAJOS 3 ENERGIA LTDA | K27: UFV TAPAJOS 3 | L27: GDs | M27: UFV TAPAJOS 3 ENERGIA LTD
J28: UFV TAPAJOS 4 ENERGIA LTDA | K28: UFV TAPAJOS 4 | L28: GDs | M28: UFV TAPAJOS 4 ENERGIA LTD
J29: UFV TAPAJOS 5 ENERGIA LTDA | K29: UFV TAPAJOS 5 | L29: GDs | M29: UFV TAPAJOS 5 ENERGIA LTD
J30: UFV ENERCRED PE 1 ENERGIA LTDA | K30: UFV ENERCRED PE 1 | L30: GDs | M30: UFV ENERCRED PE 1 ENERGIA
J31: UFV PROPRIA 1 ENERGIA LTDA | K31: UFV PROPRIA | L31: GDs | M31: UFV PROPRIA 1 ENERGIA LTD
J32: UFV PRESIDENTE 1 ENERGIA LTDA | K32: UFV PRESIDENTE 1 | L32: GDs | M32: UFV PRESIDENTE 1 ENERGIA
J33: UFV PRESIDENTE 2 ENERGIA LTDA | K33: UFV PRESIDENTE 2 | L33: GDs | M33: UFV PRESIDENTE 2 ENERGIA
... J81: UFV PAJEU III GERACAO DE ENERGIA SPE LTDA | K81: UFV PAJEU III | L81: GDs | M81: UFV PAJEU III GERACAO DE

Sheet De x Para DRE
B2: Código da conta | C2: Nome da conta | D2: De-Para Balanço IG | E2: DE-Para DRE IG | J2: Agrupamento
B3: 3110100101 | C3: VENDA DE ENERGIA ELÉTRICA | D3: 2.4 Lucros (Prejuízos) Acumulados | E3: 4.1 Receita Bruta Venda de Energia | J3: 3.2 Depreciação/Amortização
B4: 3110100102 | C4: RECEITA C/ NOTAS DE DEBITOS - TUSD E RETUSD | D4: 2.4 Lucros (Prejuízos) Acumulados | E4: 4.1 Receita Bruta Venda de Energia | J4: 3.2 Despesas financeiras
B5: 3110100103 | C5: RECEITA DE LIQUIDAÇÃO FINANCEIRA CCEE | D5: 2.4 Lucros (Prejuízos) Acumulados | E5: 4.1 (+) Liquidações CCEE Receber | J5: 3.2 Project Finance
B6: 3110100104 | C6: RECEITA COM VENDA DE I-REC | D6: 2.4 Lucros (Prejuízos) Acumulados | E6: 4.1 Receita Bruta Venda de Energia | J6: 3.2 Receitas financeiras
B7: 3110100105 | C7: RECEITA C/ NDS TAXAS CCEE VAREJISTAS | D7: 2.4 Lucros (Prejuízos) Acumulados | E7: 4.1 Receita Bruta Venda de Energia | J7: 3.1 G&A
B8: 3110200101 | C8: VENDA SERVIÇO GESTÃO DE ENERGIA | D8: 2.4 Lucros (Prejuízos) Acumulados | E8: 4.1 Receita Bruta sobre Serviços | J8: 3.1 Despesas com pessoal
B9: 3110200102 | C9: VENDA SERVIÇO DE ENERGIA SOLAR | D9: 2.4 Lucros (Prejuízos) Acumulados | E9: 4.1 Receita Bruta sobre Geração | J9: 3.3 TUSD
B10: 3110200103 | C10: VENDA SERVIÇO GESTÃO CONSUMIDORES VAREJO | D10: 2.4 Lucros (Prejuízos) Acumulados | E10: 4.1 Receita Bruta sobre Serviços | J10: 3.4 O&M
B11: 3110200104 | C11: SERVIÇO UP FRONT MKT CONSUMIDORES VAREJO | D11: 2.4 Lucros (Prejuízos) Acumulados | E11: 4.1 Receita Bruta sobre Serviços
B12: 3110200105 | C12: RECEITA GERAÇÃO DE ENERGIA COMPARTILHADA | D12: 2.4 Lucros (Prejuízos) Acumulados | E12: 4.1 Receita Bruta Venda de Energia
B13: 3110300101 | C13: RECEITA ALUGUEL IMÓVEIS | D13: 2.4 Lucros (Prejuízos) Acumulados | E13: 4.1 Receita Bruta sobre Geração
B14: 3110400101 | C14: PROVISÃO VENDA DE ENERGIA - CONTRATOS FUTUROS | D14: 2.4 Lucros (Prejuízos) Acumulados | E14: 4.1 Provisão venda de Energia - Trading
B15: 3110400102 | C15: REVERSÃO PROV. VENDA DE ENERGIA - CONTRATOS FUTUROS | D15: 2.4 Lucros (Prejuízos) Acumulados | E15: 4.1 Reversão Provisão venda de Energia - Trading
B16: 3120100101 | C16: DEV E ANULAÇÃO DE VENDAS | D16: 2.4 Lucros (Prejuízos) Acumulados | E16: 4.1 (-) Deduções
B17: 3120100102 | C17: ABATIMENTOS CONCEDIDOS | D17: 2.4 Lucros (Prejuízos) Acumulados | E17: 4.1 (-) Deduções
B18: 3120100103 | C18: DESCONTOS CONCEDIDOS | D18: 2.4 Lucros (Prejuízos) Acumulados | E18: 4.1 (-) Deduções
B19: 3120100201 | C19: (-) IPI | D19: 2.4 Lucros (Prejuízos) Acumulados | E19: 4.1 (-) Deduções
B20: 3120100202 | C20: (-) PIS | D20: 2.4 Lucros (Prejuízos) Acumulados | E20: 4.1 (-) Deduções
B21: 3120100203 | C21: (-) COFINS | D21: 2.4 Lucros (Prejuízos) Acumulados | E21: 4.1 (-) Deduções
B22: 3120100204 | C22: (-) ICMS | D22: 2.4 Lucros (Prejuízos) Acumulados | E22: 4.1 (-) Deduções
... B210: 5210100203 | C210: REVERSÃO DE PROVISÃO CSLL DIFERIDO | D210: 2.4 Lucros (Prejuízos) Acumulados | E210: 5.1 IR e CSLL Diferido

Sheet Resumo
B2: CENTRO DE CUSTO | C2: TODOS
C3: G&A | XFD3: C104
B4: Filial | C4: Orçado 2026 | D4: Previsto 2026 | E4: Orçado 2027 | F4: Status | XFD4: C202
B5: TOTAL | C5: =SUM(C6:C84) -> 1848174.3 | D5: =SUM(D6:D84) -> 1764198 | E5: =SUM(E6:E84) -> 1772362 | XFD5: TODOS
B6: ECEL COMERCIALIZADORA | C6: =IF($C$2="TODOS",SUMIFS('Orçamento 2027 - G&A'!$W:$W,'Orçamento 2027 - G&A'!$B:$B,Resumo!$B6),SUMIFS('Orçamento 2027 - G&A'!$W:$W,'Orçamento 2027 - G&A'!$B:$B,Resumo!$B6,'Orçamento 2027 - G&A'!$D:$D,Resumo!$C$2)) -> 1848174.3 | D6: =IF($C$2="TODOS",SUMIFS('Orçamento 2027 - G&A'!$AK:$AK,'Orçamento 2027 - G&A'!$B:$B,Resumo!$B6),SUMIFS('Orçamento 2027 - G&A'!$AK:$AK,'Orçamento 2027 - G&A'!$B:$B,Resumo!$B6,'Orçamento 2027 - G&A'!$D:$D,Resumo!$C$2)) -> 1764198 | E6: =IF($C$2="TODOS",SUMIFS('Orçamento 2027 - G&A'!$AX:$AX,'Orçamento 2027 - G&A'!$B:$B,Resumo!$B6),SUMIFS('Orçamento 2027 - G&A'!$AX:$AX,'Orçamento 2027 - G&A'!$B:$B,Resumo!$B6,'Orçamento 2027 - G&A'!$D:$D,Resumo!$C$2)) -> 1772362 | F6: =IF(AND(E6=0,D6<>0),"PENDENTE","OK") -> OK
B7: MERCURIA COMERCIALIZADORA | C7: =IF($C$2="TODOS",SUMIFS('Orçamento 2027 - G&A'!$W:$W,'Orçamento 2027 - G&A'!$B:$B,Resumo!$B7),SUMIFS('Orçamento 2027 - G&A'!$W:$W,'Orçamento 2027 - G&A'!$B:$B,Resumo!$B7,'Orçamento 2027 - G&A'!$D:$D,Resumo!$C$2)) -> 0 | D7: =IF($C$2="TODOS",SUMIFS('Orçamento 2027 - G&A'!$AK:$AK,'Orçamento 2027 - G&A'!$B:$B,Resumo!$B7),SUMIFS('Orçamento 2027 - G&A'!$AK:$AK,'Orçamento 2027 - G&A'!$B:$B,Resumo!$B7,'Orçamento 2027 - G&A'!$D:$D,Resumo!$C$2)) -> 0 | E7: =IF($C$2="TODOS",SUMIFS('Orçamento 2027 - G&A'!$AX:$AX,'Orçamento 2027 - G&A'!$B:$B,Resumo!$B7),SUMIFS('Orçamento 2027 - G&A'!$AX:$AX,'Orçamento 2027 - G&A'!$B:$B,Resumo!$B7,'Orçamento 2027 - G&A'!$D:$D,Resumo!$C$2)) -> 0 | F7: =IF(AND(E7=0,D7<>0),"PENDENTE","OK") -> OK
B8: ELETRON POWER GERACAO | C8: =IF($C$2="TODOS",SUMIFS('Orçamento 2027 - G&A'!$W:$W,'Orçamento 2027 - G&A'!$B:$B,Resumo!$B8),SUMIFS('Orçamento 2027 - G&A'!$W:$W,'Orçamento 2027 - G&A'!$B:$B,Resumo!$B8,'Orçamento 2027 - G&A'!$D:$D,Resumo!$C$2)) -> 0 | D8: =IF($C$2="TODOS",SUMIFS('Orçamento 2027 - G&A'!$AK:$AK,'Orçamento 2027 - G&A'!$B:$B,Resumo!$B8),SUMIFS('Orçamento 2027 - G&A'!$AK:$AK,'Orçamento 2027 - G&A'!$B:$B,Resumo!$B8,'Orçamento 2027 - G&A'!$D:$D,Resumo!$C$2)) -> 0 | E8: =IF($C$2="TODOS",SUMIFS('Orçamento 2027 - G&A'!$AX:$AX,'Orçamento 2027 - G&A'!$B:$B,Resumo!$B8),SUMIFS('Orçamento 2027 - G&A'!$AX:$AX,'Orçamento 2027 - G&A'!$B:$B,Resumo!$B8,'Orçamento 2027 - G&A'!$D:$D,Resumo!$C$2)) -> 0 | F8: =IF(AND(E8=0,D8<>0),"PENDENTE","OK") -> OK
B9: UFV IBIMIRIM 1 | C9: =IF($C$2="TODOS",SUMIFS('Orçamento 2027 - G&A'!$W:$W,'Orçamento 2027 - G&A'!$B:$B,Resumo!$B9),SUMIFS('Orçamento 2027 - G&A'!$W:$W,'Orçamento 2027 - G&A'!$B:$B,Resumo!$B9,'Orçamento 2027 - G&A'!$D:$D,Resumo!$C$2)) -> 0 | D9: =IF($C$2="TODOS",SUMIFS('Orçamento 2027 - G&A'!$AK:$AK,'Orçamento 2027 - G&A'!$B:$B,Resumo!$B9),SUMIFS('Orçamento 2027 - G&A'!$AK:$AK,'Orçamento 2027 - G&A'!$B:$B,Resumo!$B9,'Orçamento 2027 - G&A'!$D:$D,Resumo!$C$2)) -> 0 | E9: =IF($C$2="TODOS",SUMIFS('Orçamento 2027 - G&A'!$AX:$AX,'Orçamento 2027 - G&A'!$B:$B,Resumo!$B9),SUMIFS('Orçamento 2027 - G&A'!$AX:$AX,'Orçamento 2027 - G&A'!$B:$B,Resumo!$B9,'Orçamento 2027 - G&A'!$D:$D,Resumo!$C$2)) -> 0 | F9: =IF(AND(E9=0,D9<>0),"PENDENTE","OK") -> OK
B10: UFV IBIMIRIM 2 | C10: =IF($C$2="TODOS",SUMIFS('Orçamento 2027 - G&A'!$W:$W,'Orçamento 2027 - G&A'!$B:$B,Resumo!$B10),SUMIFS('Orçamento 2027 - G&A'!$W:$W,'Orçamento 2027 - G&A'!$B:$B,Resumo!$B10,'Orçamento 2027 - G&A'!$D:$D,Resumo!$C$2)) -> 0 | D10: =IF($C$2="TODOS",SUMIFS('Orçamento 2027 - G&A'!$AK:$AK,'Orçamento 2027 - G&A'!$B:$B,Resumo!$B10),SUMIFS('Orçamento 2027 - G&A'!$AK:$AK,'Orçamento 2027 - G&A'!$B:$B,Resumo!$B10,'Orçamento 2027 - G&A'!$D:$D,Resumo!$C$2)) -> 0 | E10: =IF($C$2="TODOS",SUMIFS('Orçamento 2027 - G&A'!$AX:$AX,'Orçamento 2027 - G&A'!$B:$B,Resumo!$B10),SUMIFS('Orçamento 2027 - G&A'!$AX:$AX,'Orçamento 2027 - G&A'!$B:$B,Resumo!$B10,'Orçamento 2027 - G&A'!$D:$D,Resumo!$C$2)) -> 0 | F10: =IF(AND(E10=0,D10<>0),"PENDENTE","OK") -> OK
B11: UFV IBIMIRIM 3 | C11: =IF($C$2="TODOS",SUMIFS('Orçamento 2027 - G&A'!$W:$W,'Orçamento 2027 - G&A'!$B:$B,Resumo!$B11),SUMIFS('Orçamento 2027 - G&A'!$W:$W,'Orçamento 2027 - G&A'!$B:$B,Resumo!$B11,'Orçamento 2027 - G&A'!$D:$D,Resumo!$C$2)) -> 0 | D11: =IF($C$2="TODOS",SUMIFS('Orçamento 2027 - G&A'!$AK:$AK,'Orçamento 2027 - G&A'!$B:$B,Resumo!$B11),SUMIFS('Orçamento 2027 - G&A'!$AK:$AK,'Orçamento 2027 - G&A'!$B:$B,Resumo!$B11,'Orçamento 2027 - G&A'!$D:$D,Resumo!$C$2)) -> 0 | E11: =IF($C$2="TODOS",SUMIFS('Orçamento 2027 - G&A'!$AX:$AX,'Orçamento 2027 - G&A'!$B:$B,Resumo!$B11),SUMIFS('Orçamento 2027 - G&A'!$AX:$AX,'Orçamento 2027 - G&A'!$B:$B,Resumo!$B11,'Orçamento 2027 - G&A'!$D:$D,Resumo!$C$2)) -> 0 | F11: =IF(AND(E11=0,D11<>0),"PENDENTE","OK") -> OK
B12: UFV IBIMIRIM 4 | C12: =IF($C$2="TODOS",SUMIFS('Orçamento 2027 - G&A'!$W:$W,'Orçamento 2027 - G&A'!$B:$B,Resumo!$B12),SUMIFS('Orçamento 2027 - G&A'!$W:$W,'Orçamento 2027 - G&A'!$B:$B,Resumo!$B12,'Orçamento 2027 - G&A'!$D:$D,Resumo!$C$2)) -> 0 | D12: =IF($C$2="TODOS",SUMIFS('Orçamento 2027 - G&A'!$AK:$AK,'Orçamento 2027 - G&A'!$B:$B,Resumo!$B12),SUMIFS('Orçamento 2027 - G&A'!$AK:$AK,'Orçamento 2027 - G&A'!$B:$B,Resumo!$B12,'Orçamento 2027 - G&A'!$D:$D,Resumo!$C$2)) -> 0 | E12: =IF($C$2="TODOS",SUMIFS('Orçamento 2027 - G&A'!$AX:$AX,'Orçamento 2027 - G&A'!$B:$B,Resumo!$B12),SUMIFS('Orçamento 2027 - G&A'!$AX:$AX,'Orçamento 2027 - G&A'!$B:$B,Resumo!$B12,'Orçamento 2027 - G&A'!$D:$D,Resumo!$C$2)) -> 0 | F12: =IF(AND(E12=0,D12<>0),"PENDENTE","OK") -> OK
B13: UFV IBIMIRIM 5 | C13: =IF($C$2="TODOS",SUMIFS('Orçamento 2027 - G&A'!$W:$W,'Orçamento 2027 - G&A'!$B:$B,Resumo!$B13),SUMIFS('Orçamento 2027 - G&A'!$W:$W,'Orçamento 2027 - G&A'!$B:$B,Resumo!$B13,'Orçamento 2027 - G&A'!$D:$D,Resumo!$C$2)) -> 0 | D13: =IF($C$2="TODOS",SUMIFS('Orçamento 2027 - G&A'!$AK:$AK,'Orçamento 2027 - G&A'!$B:$B,Resumo!$B13),SUMIFS('Orçamento 2027 - G&A'!$AK:$AK,'Orçamento 2027 - G&A'!$B:$B,Resumo!$B13,'Orçamento 2027 - G&A'!$D:$D,Resumo!$C$2)) -> 0 | E13: =IF($C$2="TODOS",SUMIFS('Orçamento 2027 - G&A'!$AX:$AX,'Orçamento 2027 - G&A'!$B:$B,Resumo!$B13),SUMIFS('Orçamento 2027 - G&A'!$AX:$AX,'Orçamento 2027 - G&A'!$B:$B,Resumo!$B13,'Orçamento 2027 - G&A'!$D:$D,Resumo!$C$2)) -> 0 | F13: =IF(AND(E13=0,D13<>0),"PENDENTE","OK") -> OK
B14: UFV IBIMIRIM 6 | C14: =IF($C$2="TODOS",SUMIFS('Orçamento 2027 - G&A'!$W:$W,'Orçamento 2027 - G&A'!$B:$B,Resumo!$B14),SUMIFS('Orçamento 2027 - G&A'!$W:$W,'Orçamento 2027 - G&A'!$B:$B,Resumo!$B14,'Orçamento 2027 - G&A'!$D:$D,Resumo!$C$2)) -> 0 | D14: =IF($C$2="TODOS",SUMIFS('Orçamento 2027 - G&A'!$AK:$AK,'Orçamento 2027 - G&A'!$B:$B,Resumo!$B14),SUMIFS('Orçamento 2027 - G&A'!$AK:$AK,'Orçamento 2027 - G&A'!$B:$B,Resumo!$B14,'Orçamento 2027 - G&A'!$D:$D,Resumo!$C$2)) -> 0 | E14: =IF($C$2="TODOS",SUMIFS('Orçamento 2027 - G&A'!$AX:$AX,'Orçamento 2027 - G&A'!$B:$B,Resumo!$B14),SUMIFS('Orçamento 2027 - G&A'!$AX:$AX,'Orçamento 2027 - G&A'!$B:$B,Resumo!$B14,'Orçamento 2027 - G&A'!$D:$D,Resumo!$C$2)) -> 0 | F14: =IF(AND(E14=0,D14<>0),"PENDENTE","OK") -> OK
B15: UFV IBIMIRIM 7 | C15: =IF($C$2="TODOS",SUMIFS('Orçamento 2027 - G&A'!$W:$W,'Orçamento 2027 - G&A'!$B:$B,Resumo!$B15),SUMIFS('Orçamento 2027 - G&A'!$W:$W,'Orçamento 2027 - G&A'!$B:$B,Resumo!$B15,'Orçamento 2027 - G&A'!$D:$D,Resumo!$C$2)) -> 0 | D15: =IF($C$2="TODOS",SUMIFS('Orçamento 2027 - G&A'!$AK:$AK,'Orçamento 2027 - G&A'!$B:$B,Resumo!$B15),SUMIFS('Orçamento 2027 - G&A'!$AK:$AK,'Orçamento 2027 - G&A'!$B:$B,Resumo!$B15,'Orçamento 2027 - G&A'!$D:$D,Resumo!$C$2)) -> 0 | E15: =IF($C$2="TODOS",SUMIFS('Orçamento 2027 - G&A'!$AX:$AX,'Orçamento 2027 - G&A'!$B:$B,Resumo!$B15),SUMIFS('Orçamento 2027 - G&A'!$AX:$AX,'Orçamento 2027 - G&A'!$B:$B,Resumo!$B15,'Orçamento 2027 - G&A'!$D:$D,Resumo!$C$2)) -> 0 | F15: =IF(AND(E15=0,D15<>0),"PENDENTE","OK") -> OK
B16: UFV IBIMIRIM 8 | C16: =IF($C$2="TODOS",SUMIFS('Orçamento 2027 - G&A'!$W:$W,'Orçamento 2027 - G&A'!$B:$B,Resumo!$B16),SUMIFS('Orçamento 2027 - G&A'!$W:$W,'Orçamento 2027 - G&A'!$B:$B,Resumo!$B16,'Orçamento 2027 - G&A'!$D:$D,Resumo!$C$2)) -> 0 | D16: =IF($C$2="TODOS",SUMIFS('Orçamento 2027 - G&A'!$AK:$AK,'Orçamento 2027 - G&A'!$B:$B,Resumo!$B16),SUMIFS('Orçamento 2027 - G&A'!$AK:$AK,'Orçamento 2027 - G&A'!$B:$B,Resumo!$B16,'Orçamento 2027 - G&A'!$D:$D,Resumo!$C$2)) -> 0 | E16: =IF($C$2="TODOS",SUMIFS('Orçamento 2027 - G&A'!$AX:$AX,'Orçamento 2027 - G&A'!$B:$B,Resumo!$B16),SUMIFS('Orçamento 2027 - G&A'!$AX:$AX,'Orçamento 2027 - G&A'!$B:$B,Resumo!$B16,'Orçamento 2027 - G&A'!$D:$D,Resumo!$C$2)) -> 0 | F16: =IF(AND(E16=0,D16<>0),"PENDENTE","OK") -> OK
B17: UFV IBIMIRIM 9 | C17: =IF($C$2="TODOS",SUMIFS('Orçamento 2027 - G&A'!$W:$W,'Orçamento 2027 - G&A'!$B:$B,Resumo!$B17),SUMIFS('Orçamento 2027 - G&A'!$W:$W,'Orçamento 2027 - G&A'!$B:$B,Resumo!$B17,'Orçamento 2027 - G&A'!$D:$D,Resumo!$C$2)) -> 0 | D17: =IF($C$2="TODOS",SUMIFS('Orçamento 2027 - G&A'!$AK:$AK,'Orçamento 2027 - G&A'!$B:$B,Resumo!$B17),SUMIFS('Orçamento 2027 - G&A'!$AK:$AK,'Orçamento 2027 - G&A'!$B:$B,Resumo!$B17,'Orçamento 2027 - G&A'!$D:$D,Resumo!$C$2)) -> 0 | E17: =IF($C$2="TODOS",SUMIFS('Orçamento 2027 - G&A'!$AX:$AX,'Orçamento 2027 - G&A'!$B:$B,Resumo!$B17),SUMIFS('Orçamento 2027 - G&A'!$AX:$AX,'Orçamento 2027 - G&A'!$B:$B,Resumo!$B17,'Orçamento 2027 - G&A'!$D:$D,Resumo!$C$2)) -> 0 | F17: =IF(AND(E17=0,D17<>0),"PENDENTE","OK") -> OK
... B84: UFV PAJEU III | C84: =IF($C$2="TODOS",SUMIFS('Orçamento 2027 - G&A'!$W:$W,'Orçamento 2027 - G&A'!$B:$B,Resumo!$B84),SUMIFS('Orçamento 2027 - G&A'!$W:$W,'Orçamento 2027 - G&A'!$B:$B,Resumo!$B84,'Orçamento 2027 - G&A'!$D:$D,Resumo!$C$2)) -> 0 | D84: =IF($C$2="TODOS",SUMIFS('Orçamento 2027 - G&A'!$AK:$AK,'Orçamento 2027 - G&A'!$B:$B,Resumo!$B84),SUMIFS('Orçamento 2027 - G&A'!$AK:$AK,'Orçamento 2027 - G&A'!$B:$B,Resumo!$B84,'Orçamento 2027 - G&A'!$D:$D,Resumo!$C$2)) -> 0 | E84: =IF($C$2="TODOS",SUMIFS('Orçamento 2027 - G&A'!$AX:$AX,'Orçamento 2027 - G&A'!$B:$B,Resumo!$B84),SUMIFS('Orçamento 2027 - G&A'!$AX:$AX,'Orçamento 2027 - G&A'!$B:$B,Resumo!$B84,'Orçamento 2027 - G&A'!$D:$D,Resumo!$C$2)) -> 0 | F84: =IF(AND(E84=0,D84<>0),"PENDENTE","OK") -> OK

Sheet Orçamento 2027 - G&A
A1: ORÇAMENTO 2027 | PLANEJAMENTO POR CENTRO DE CUSTO
A3: Como usar: filtre Centro de Custo ou Responsável no cabeçalho da tabela, selecione Filial e Conta, preencha os valores mensais em azul e finalize a linha quando a proposta estiver revisada. O histórico será trazido automaticamente após a carga na aba Base Histórico.
A4: Legenda: azul = entrada do gestor | verde = vínculo automático | preto = cálculo
A6: IDENTIFICAÇÃO | K6: ORÇAMENTO 2026 | X6: PROJETADO 2026 | AJ6: HISTÓRICO | AL6: ORÇAMENTO 2027 | ENTRADAS MENSAIS | AX6: TOTAL E VARIAÇÃO | BA6: GESTÃO
A7: Linha | B7: Filial | C7: Cluster | D7: Centro de Custo | E7: Diretoria | F7: Responsável | G7: =IF($H7="","",IFERROR(_xlfn.XLOOKUP(H7,'De x Para DRE'!C:C,'De x Para DRE'!B:B),"")) -> Código da conta | H7: Nome da Conta | I7: Linha DRE | J7: Descrição | K7: Jan | L7: Fev | M7: Mar | N7: Abr | O7: Mai | P7: Jun | Q7: Jul | R7: Ago | S7: Set | T7: Out | U7: Nov | V7: Dez | W7: Orçado 2026 | X7: Jan | Y7: Fev | Z7: Mar | AA7: Abr | AB7: Mai | AC7: Jun | AD7: Jul | AE7: Ago | AF7: Set | AG7: Out | AH7: Nov | AI7: Dez | AJ7: Real 2026 YTD | AK7: Projeção 2026 | AL7: Jan | AM7: Fev | AN7: Mar | AO7: Abr | AP7: Mai | AQ7: Jun | AR7: Jul | AS7: Ago | AT7: Set | AU7: Out | AV7: Nov | AW7: Dez | AX7: Orçado 2027 | AY7: Var. R$ vs 2026 Orç. | AZ7: Var. R$ vs 2026 Proj. | BA7: Justificativa | BB7: Status
A8: =IF(OR($B8="",$D8="",$G8=""),"",ROW()-7) -> 1 | B8: ECEL COMERCIALIZADORA | C8: =IF($B8="","",IFERROR(INDEX(Apoio!$L$3:$L$81,MATCH($B8,Apoio!$K$3:$K$81,0)),"")) -> COMERCIALIZADORA | D8: C104 | E8: =IF($D8="","",IFERROR(INDEX(Apoio!$C$3:$C$81,MATCH($D8,Apoio!$B$3:$B$81,0)),"")) -> TI | F8: =IF($D8="","",IFERROR(INDEX(Apoio!$D$3:$D$81,MATCH($D8,Apoio!$B$3:$B$81,0)),"")) -> Marcelo Bronzatti | G8: =IF($H8="","",IFERROR(_xlfn.XLOOKUP(H8,'De x Para DRE'!C:C,'De x Para DRE'!B:B),"")) -> 5110100702 | H8: SISTEMAS DE GESTÃO ADM/OPERACIONAL | I8: =IF($G8="","",IFERROR(INDEX('De x Para DRE'!$E$3:$E$210,MATCH($G8,'De x Para DRE'!$B$3:$B$210,0)),"")) -> 3.1 G&A | J8: Consultoria SAP - Alfa | K8: 30600 | L8: 30600 | M8: 30600 | N8: 30600 | O8: 30600 | P8: 30600 | W8: =SUM(K8:V8) -> 183600 | X8: 29404.52 | Y8: 30658.45 | Z8: 30658.45 | AA8: 30658.45 | AB8: =25604.15+5054.3 -> 30658.45 | AC8: =2381.25+458.84+22764.06+5054.3 -> 30658.45 | AD8: 0 | AE8: 0 | AG8: 0 | AH8: 0 | AI8: 0 | AJ8: =SUM(X8:AE8) -> 182696.77 | AK8: =SUM(X8:AI8) -> 182696.77 | AL8: 0 | AM8: 0 | AN8: 0 | AO8: 0 | AP8: 0 | AQ8: 0 | AR8: 0 | AS8: 0 | AT8: 0 | AU8: 0 | AV8: 0 | AW8: 0 | AX8: =IF(COUNT($AL8:$AW8)=0,"",SUM($AL8:$AW8)) -> 0 | AY8: =IF($AX8="","",$AX8-IF($W8="",0,$W8)) -> -183600 | AZ8: =IF($AX8="","",$AX8-IF($AK8="",0,$AK8)) -> -182696.77 | BB8: Rascunho
A9: =IF(OR($B9="",$D9="",$G9=""),"",ROW()-7) -> 2 | B9: ECEL COMERCIALIZADORA | C9: =IF($B9="","",IFERROR(INDEX(Apoio!$L$3:$L$81,MATCH($B9,Apoio!$K$3:$K$81,0)),"")) -> COMERCIALIZADORA | D9: C104 | E9: =IF($D9="","",IFERROR(INDEX(Apoio!$C$3:$C$81,MATCH($D9,Apoio!$B$3:$B$81,0)),"")) -> TI | F9: =IF($D9="","",IFERROR(INDEX(Apoio!$D$3:$D$81,MATCH($D9,Apoio!$B$3:$B$81,0)),"")) -> Marcelo Bronzatti | G9: =IF($H9="","",IFERROR(_xlfn.XLOOKUP(H9,'De x Para DRE'!C:C,'De x Para DRE'!B:B),"")) -> 5110100702 | H9: SISTEMAS DE GESTÃO ADM/OPERACIONAL | I9: =IF($G9="","",IFERROR(INDEX('De x Para DRE'!$E$3:$E$210,MATCH($G9,'De x Para DRE'!$B$3:$B$210,0)),"")) -> 3.1 G&A | J9: Consultoria SAP - Ramo | M9: 4000 | N9: 4000 | O9: =4000+2720+3685.13 -> 10405.13 | P9: =4000+2720+3685.13 -> 10405.13 | Q9: =4000+2720+3685.13+16716 -> 27121.13 | R9: =4000+2720+3685.13+16716 -> 27121.13 | S9: =4000+2720+3685.13+16716 -> 27121.13 | T9: =4000+2720+3685.13+16716 -> 27121.13 | U9: =4000+16716 -> 20716 | V9: =4000+16716 -> 20716 | W9: =SUM(K9:V9) -> 178726.78 | X9: =2975.75 -> 2975.75 | Y9: =2975.75 -> 2975.75 | AA9: =5029.16+3202.57+16716 -> 24947.73 | AB9: =3202.57+16716+5029.16 -> 24947.73 | AC9: =3202.57+15251+5029.16 -> 23482.73 | AD9: =15251+5029.16+3202.57 -> 23482.73 | AE9: 23482.73 | AF9: 23482.73 | AG9: 23482.73 | AH9: 23482.73 | AI9: 23482.73 | AJ9: =SUM(X9:AE9) -> 126295.15 | AK9: =SUM(X9:AI9) -> 220226.07 | AL9: 16000 | AM9: 16000 | AN9: 16000 | AO9: 16000 | AP9: 16000 | AQ9: 16000 | AR9: 16000 | AS9: 16000 | AT9: 16000 | AU9: 16000 | AV9: 16000 | AW9: 16000 | AX9: =IF(COUNT($AL9:$AW9)=0,"",SUM($AL9:$AW9)) -> 192000 | AY9: =IF($AX9="","",$AX9-IF($W9="",0,$W9)) -> 13273.22 | AZ9: =IF($AX9="","",$AX9-IF($AK9="",0,$AK9)) -> -28226.07 | BA9: REAJUSTE IGPM | BB9: Rascunho
A10: =IF(OR($B10="",$D10="",$G10=""),"",ROW()-7) -> 3 | B10: ECEL COMERCIALIZADORA | C10: =IF($B10="","",IFERROR(INDEX(Apoio!$L$3:$L$81,MATCH($B10,Apoio!$K$3:$K$81,0)),"")) -> COMERCIALIZADORA | D10: C104 | E10: =IF($D10="","",IFERROR(INDEX(Apoio!$C$3:$C$81,MATCH($D10,Apoio!$B$3:$B$81,0)),"")) -> TI | F10: =IF($D10="","",IFERROR(INDEX(Apoio!$D$3:$D$81,MATCH($D10,Apoio!$B$3:$B$81,0)),"")) -> Marcelo Bronzatti | G10: =IF($H10="","",IFERROR(_xlfn.XLOOKUP(H10,'De x Para DRE'!C:C,'De x Para DRE'!B:B),"")) -> 5110100702 | H10: SISTEMAS DE GESTÃO ADM/OPERACIONAL | I10: =IF($G10="","",IFERROR(INDEX('De x Para DRE'!$E$3:$E$210,MATCH($G10,'De x Para DRE'!$B$3:$B$210,0)),"")) -> 3.1 G&A | J10: StarSoft - Sistema Folha de Pagamento | K10: 1950 | L10: 1950 | M10: 1950 | N10: 1950 | O10: 1950 | P10: 1950 | Q10: 2047.5 | R10: 2047.5 | S10: 2047.5 | T10: 2047.5 | U10: 2047.5 | V10: 2047.5 | W10: =SUM(K10:V10) -> 23985 | X10: 1950 | Y10: 1950 | Z10: 1950 | AA10: 1950 | AB10: 1950 | AD10: 0 | AE10: 0 | AF10: 0 | AG10: 0 | AH10: 0 | AI10: 0 | AJ10: =SUM(X10:AE10) -> 9750 | AK10: =SUM(X10:AI10) -> 9750 | AL10: 0 | AM10: 0 | AN10: 0 | AO10: 0 | AP10: 0 | AQ10: 0 | AR10: 0 | AS10: 0 | AT10: 0 | AU10: 0 | AV10: 0 | AW10: 0 | AX10: =IF(COUNT($AL10:$AW10)=0,"",SUM($AL10:$AW10)) -> 0 | AY10: =IF($AX10="","",$AX10-IF($W10="",0,$W10)) -> -23985 | AZ10: =IF($AX10="","",$AX10-IF($AK10="",0,$AK10)) -> -9750 | BB10: Rascunho
A11: =IF(OR($B11="",$D11="",$G11=""),"",ROW()-7) -> 4 | B11: ECEL COMERCIALIZADORA | C11: =IF($B11="","",IFERROR(INDEX(Apoio!$L$3:$L$81,MATCH($B11,Apoio!$K$3:$K$81,0)),"")) -> COMERCIALIZADORA | D11: C104 | E11: =IF($D11="","",IFERROR(INDEX(Apoio!$C$3:$C$81,MATCH($D11,Apoio!$B$3:$B$81,0)),"")) -> TI | F11: =IF($D11="","",IFERROR(INDEX(Apoio!$D$3:$D$81,MATCH($D11,Apoio!$B$3:$B$81,0)),"")) -> Marcelo Bronzatti | G11: =IF($H11="","",IFERROR(_xlfn.XLOOKUP(H11,'De x Para DRE'!C:C,'De x Para DRE'!B:B),"")) -> 5110100702 | H11: SISTEMAS DE GESTÃO ADM/OPERACIONAL | I11: =IF($G11="","",IFERROR(INDEX('De x Para DRE'!$E$3:$E$210,MATCH($G11,'De x Para DRE'!$B$3:$B$210,0)),"")) -> 3.1 G&A | J11: TopDesk - Sistema de Chamados TI | K11: 7234 | L11: 7234 | M11: 7234 | N11: 7547.02 | O11: 7547.02 | P11: 7547.02 | Q11: 7547.02 | R11: 7547.02 | S11: 7547.02 | T11: 7547.02 | U11: 7547.02 | V11: 7547.02 | W11: =SUM(K11:V11) -> 89625.18 | X11: 7233.5 | Y11: 7233.5 | Z11: 7233.5 | AA11: 15089.08 | AB11: 7544.54 | AC11: 7544.54 | AD11: 5014.46 | AE11: 5014.46 | AF11: 5014.46 | AG11: 5014.46 | AH11: 5014.46 | AI11: 5014.46 | AJ11: =SUM(X11:AE11) -> 61907.58 | AK11: =SUM(X11:AI11) -> 81965.42 | AL11: 5015 | AM11: 5015 | AN11: 5015 | AO11: 5015 | AP11: 0 | AQ11: 0 | AR11: 0 | AS11: 0 | AT11: 0 | AU11: 0 | AV11: 0 | AW11: 0 | AX11: =IF(COUNT($AL11:$AW11)=0,"",SUM($AL11:$AW11)) -> 20060 | AY11: =IF($AX11="","",$AX11-IF($W11="",0,$W11)) -> -69565.18 | AZ11: =IF($AX11="","",$AX11-IF($AK11="",0,$AK11)) -> -61905.42 | BA11: RESCISÃO EM 31/03/27 | BB11: Rascunho
A12: =IF(OR($B12="",$D12="",$G12=""),"",ROW()-7) -> 5 | B12: ECEL COMERCIALIZADORA | C12: =IF($B12="","",IFERROR(INDEX(Apoio!$L$3:$L$81,MATCH($B12,Apoio!$K$3:$K$81,0)),"")) -> COMERCIALIZADORA | D12: C104 | E12: =IF($D12="","",IFERROR(INDEX(Apoio!$C$3:$C$81,MATCH($D12,Apoio!$B$3:$B$81,0)),"")) -> TI | F12: =IF($D12="","",IFERROR(INDEX(Apoio!$D$3:$D$81,MATCH($D12,Apoio!$B$3:$B$81,0)),"")) -> Marcelo Bronzatti | G12: =IF($H12="","",IFERROR(_xlfn.XLOOKUP(H12,'De x Para DRE'!C:C,'De x Para DRE'!B:B),"")) -> 5110100702 | H12: SISTEMAS DE GESTÃO ADM/OPERACIONAL | I12: =IF($G12="","",IFERROR(INDEX('De x Para DRE'!$E$3:$E$210,MATCH($G12,'De x Para DRE'!$B$3:$B$210,0)),"")) -> 3.1 G&A | J12: SKYOne | K12: 4232 | L12: 4232 | M12: 4232 | N12: =4232+5894 -> 10126 | O12: =4232+5894 -> 10126 | P12: =4232+5894 -> 10126 | Q12: =4443.6+5894 -> 10337.6 | R12: =4443.6+5894 -> 10337.6 | S12: =4443.6+5894 -> 10337.6 | T12: =4443.6+5894 -> 10337.6 | U12: =4443.6+5894 -> 10337.6 | V12: =4443.6+5894 -> 10337.6 | W12: =SUM(K12:V12) -> 105099.6 | X12: 0 | Y12: 8464.42 | Z12: 0 | AA12: 10706.3 | AB12: =3785.4+2688.69+4232.21 -> 10706.3 | AC12: =2688.69+3785.4+2688.69+3785.4+4232.21 -> 17180.39 | AD12: 10706.3 | AE12: 10706.3 | AF12: 10706.3 | AG12: 10706.3 | AH12: 10706.3 | AI12: 10706.3 | AJ12: =SUM(X12:AE12) -> 68470.01 | AK12: =SUM(X12:AI12) -> 111295.21 | AL12: 11000 | AM12: 11000 | AN12: 11500 | AO12: 11500 | AP12: 11500 | AQ12: 11500 | AR12: 11500 | AS12: 11500 | AT12: 11500 | AU12: 11500 | AV12: 11500 | AW12: 11500 | AX12: =IF(COUNT($AL12:$AW12)=0,"",SUM($AL12:$AW12)) -> 137000 | AY12: =IF($AX12="","",$AX12-IF($W12="",0,$W12)) -> 31900.4 | AZ12: =IF($AX12="","",$AX12-IF($AK12="",0,$AK12)) -> 25704.79 | BA12: REAJUSTE IGPM STUDIO SKU - 4500,00 AUTOSKY - 6500,00 | BB12: Rascunho
A13: =IF(OR($B13="",$D13="",$G13=""),"",ROW()-7) -> 6 | B13: ECEL COMERCIALIZADORA | C13: =IF($B13="","",IFERROR(INDEX(Apoio!$L$3:$L$81,MATCH($B13,Apoio!$K$3:$K$81,0)),"")) -> COMERCIALIZADORA | D13: C104 | E13: =IF($D13="","",IFERROR(INDEX(Apoio!$C$3:$C$81,MATCH($D13,Apoio!$B$3:$B$81,0)),"")) -> TI | F13: =IF($D13="","",IFERROR(INDEX(Apoio!$D$3:$D$81,MATCH($D13,Apoio!$B$3:$B$81,0)),"")) -> Marcelo Bronzatti | G13: =IF($H13="","",IFERROR(_xlfn.XLOOKUP(H13,'De x Para DRE'!C:C,'De x Para DRE'!B:B),"")) -> 5110100702 | H13: SISTEMAS DE GESTÃO ADM/OPERACIONAL | I13: =IF($G13="","",IFERROR(INDEX('De x Para DRE'!$E$3:$E$210,MATCH($G13,'De x Para DRE'!$B$3:$B$210,0)),"")) -> 3.1 G&A | J13: ClickSign - Assinatura Documentos | K13: 789 | L13: 789 | M13: 789 | N13: 789 | O13: 789 | P13: 789 | Q13: 828.45 | R13: 828.45 | S13: 828.45 | T13: 828.45 | U13: 828.45 | V13: 828.45 | W13: =SUM(K13:V13) -> 9704.7 | X13: =789+789 -> 1578 | Y13: 789 | Z13: 789 | AA13: 789 | AB13: 789 | AC13: 789 | AD13: 789 | AE13: 795.96 | AF13: 795.96 | AG13: 795.96 | AH13: 795.96 | AI13: 795.96 | AJ13: =SUM(X13:AE13) -> 7107.96 | AK13: =SUM(X13:AI13) -> 10291.8 | AL13: 830 | AM13: 830 | AN13: 830 | AO13: 830 | AP13: 830 | AQ13: 830 | AR13: 830 | AS13: 860 | AT13: 860 | AU13: 860 | AV13: 860 | AW13: 860 | AX13: =IF(COUNT($AL13:$AW13)=0,"",SUM($AL13:$AW13)) -> 10110 | AY13: =IF($AX13="","",$AX13-IF($W13="",0,$W13)) -> 405.3 | AZ13: =IF($AX13="","",$AX13-IF($AK13="",0,$AK13)) -> -181.8 | BB13: Rascunho
A14: =IF(OR($B14="",$D14="",$G14=""),"",ROW()-7) -> 7 | B14: ECEL COMERCIALIZADORA | C14: =IF($B14="","",IFERROR(INDEX(Apoio!$L$3:$L$81,MATCH($B14,Apoio!$K$3:$K$81,0)),"")) -> COMERCIALIZADORA | D14: C104 | E14: =IF($D14="","",IFERROR(INDEX(Apoio!$C$3:$C$81,MATCH($D14,Apoio!$B$3:$B$81,0)),"")) -> TI | F14: =IF($D14="","",IFERROR(INDEX(Apoio!$D$3:$D$81,MATCH($D14,Apoio!$B$3:$B$81,0)),"")) -> Marcelo Bronzatti | G14: =IF($H14="","",IFERROR(_xlfn.XLOOKUP(H14,'De x Para DRE'!C:C,'De x Para DRE'!B:B),"")) -> 5110100702 | H14: SISTEMAS DE GESTÃO ADM/OPERACIONAL | I14: =IF($G14="","",IFERROR(INDEX('De x Para DRE'!$E$3:$E$210,MATCH($G14,'De x Para DRE'!$B$3:$B$210,0)),"")) -> 3.1 G&A | J14: Paradigma - Sistema BackOffice | K14: 36714 | L14: 36714 | M14: 36714 | N14: 36714 | O14: 36714 | P14: 36714 | Q14: 38549.7 | R14: 38549.7 | S14: 38549.7 | T14: 38549.7 | U14: 38549.7 | V14: 38549.7 | W14: =SUM(K14:V14) -> 451582.2 | X14: =1500+10000+25213.83 -> 36713.83 | Y14: =3000+10000+25213.83-1500 -> 36713.83 | Z14: =1500+10000+25213.83 -> 36713.83 | AA14: =1891.02+10000+25213.83+2130.34 -> 39235.19 | AB14: =10000+25213.83+1800+2130.34 -> 39144.17 | AC14: =10000+15877.79+2130.34 -> 28008.13 | AD14: =15877.79+10000+2130.34 -> 28008.13 | AE14: =15877.79+10000+2130.34 -> 28008.13 | AF14: 28008.13 | AG14: 28008.13 | AH14: 28008.13 | AI14: 28008.13 | AJ14: =SUM(X14:AE14) -> 272545.24 | AK14: =SUM(X14:AI14) -> 384577.76 | AL14: 36800 | AM14: 36800 | AN14: 36800 | AO14: 38400 | AP14: 38400 | AQ14: 38400 | AR14: 38400 | AS14: 38400 | AT14: 38400 | AU14: 38400 | AV14: 38400 | AW14: 38400 | AX14: =IF(COUNT($AL14:$AW14)=0,"",SUM($AL14:$AW14)) -> 456000 | AY14: =IF($AX14="","",$AX14-IF($W14="",0,$W14)) -> 4417.8 | AZ14: =IF($AX14="","",$AX14-IF($AK14="",0,$AK14)) -> 71422.24 | BA14: RETORNO DO VALOR RENEG E REAJUSTE IGPM *DEVE SER FEITO AVISO PREVIO EM JAN/27 E MIGRAR PARA BOLETADOR* | BB14: Rascunho
A15: =IF(OR($B15="",$D15="",$G15=""),"",ROW()-7) -> 8 | B15: ECEL COMERCIALIZADORA | C15: =IF($B15="","",IFERROR(INDEX(Apoio!$L$3:$L$81,MATCH($B15,Apoio!$K$3:$K$81,0)),"")) -> COMERCIALIZADORA | D15: C104 | E15: =IF($D15="","",IFERROR(INDEX(Apoio!$C$3:$C$81,MATCH($D15,Apoio!$B$3:$B$81,0)),"")) -> TI | F15: =IF($D15="","",IFERROR(INDEX(Apoio!$D$3:$D$81,MATCH($D15,Apoio!$B$3:$B$81,0)),"")) -> Marcelo Bronzatti | G15: =IF($H15="","",IFERROR(_xlfn.XLOOKUP(H15,'De x Para DRE'!C:C,'De x Para DRE'!B:B),"")) -> 5110100702 | H15: SISTEMAS DE GESTÃO ADM/OPERACIONAL | I15: =IF($G15="","",IFERROR(INDEX('De x Para DRE'!$E$3:$E$210,MATCH($G15,'De x Para DRE'!$B$3:$B$210,0)),"")) -> 3.1 G&A | J15: TeamGuide - Sistema de Gestão de Pessoas | K15: 1705 | L15: 1705 | M15: 1705 | N15: 1705 | O15: 1705 | P15: 1705 | Q15: 1449.25 | R15: 1449.25 | S15: 1449.25 | T15: 1449.25 | U15: 1449.25 | V15: 1449.25 | W15: =SUM(K15:V15) -> 18925.5 | X15: 1272 | Y15: =1188+264 -> 1452 | Z15: =1068 -> 1068 | AA15: =1056+288+72+72 -> 1488 | AB15: =1188+60 -> 1248 | AC15: =1068+60 -> 1128 | AD15: 1092 | AE15: 1116 | AF15: =AE15 -> 1116 | AG15: =AF15 -> 1116 | AH15: =AG15 -> 1116 | AI15: =AH15 -> 1116 | AJ15: =SUM(X15:AE15) -> 9864 | AK15: =SUM(X15:AI15) -> 14328 | AL15: 0 | AM15: 0 | AN15: 0 | AO15: 0 | AP15: 0 | AQ15: 0 | AR15: 0 | AS15: 0 | AT15: 0 | AU15: 0 | AV15: 0 | AW15: 0 | AX15: =IF(COUNT($AL15:$AW15)=0,"",SUM($AL15:$AW15)) -> 0 | AY15: =IF($AX15="","",$AX15-IF($W15="",0,$W15)) -> -18925.5 | AZ15: =IF($AX15="","",$AX15-IF($AK15="",0,$AK15)) -> -14328 | BB15: Rascunho
A16: =IF(OR($B16="",$D16="",$G16=""),"",ROW()-7) -> 9 | B16: ECEL COMERCIALIZADORA | C16: =IF($B16="","",IFERROR(INDEX(Apoio!$L$3:$L$81,MATCH($B16,Apoio!$K$3:$K$81,0)),"")) -> COMERCIALIZADORA | D16: C104 | E16: =IF($D16="","",IFERROR(INDEX(Apoio!$C$3:$C$81,MATCH($D16,Apoio!$B$3:$B$81,0)),"")) -> TI | F16: =IF($D16="","",IFERROR(INDEX(Apoio!$D$3:$D$81,MATCH($D16,Apoio!$B$3:$B$81,0)),"")) -> Marcelo Bronzatti | G16: =IF($H16="","",IFERROR(_xlfn.XLOOKUP(H16,'De x Para DRE'!C:C,'De x Para DRE'!B:B),"")) -> 5110100702 | H16: SISTEMAS DE GESTÃO ADM/OPERACIONAL | I16: =IF($G16="","",IFERROR(INDEX('De x Para DRE'!$E$3:$E$210,MATCH($G16,'De x Para DRE'!$B$3:$B$210,0)),"")) -> 3.1 G&A | J16: Colmeia - Sistema | K16: 1700 | L16: 1700 | M16: 1700 | N16: 2000 | O16: 2000 | P16: 2000 | Q16: 2000 | R16: 2500 | S16: 2500 | T16: 2500 | U16: 2500 | V16: 2500 | W16: =SUM(K16:V16) -> 25600 | X16: 3320.71 | Y16: 1541.21 | Z16: 1840.61 | AA16: 1497.47 | AB16: 2333.88 | AC16: 3053.31 | AD16: =3678.65 -> 3678.65 | AE16: =3267.99 -> 3267.99 | AF16: =AE16 -> 3267.99 | AG16: =AF16 -> 3267.99 | AH16: =AG16 -> 3267.99 | AI16: =AH16 -> 3267.99 | AJ16: =SUM(X16:AE16) -> 20533.83 | AK16: =SUM(X16:AI16) -> 33605.79 | AL16: 5000 | AM16: 5000 | AN16: 5000 | AO16: 5000 | AP16: 6500 | AQ16: 6500 | AR16: 6500 | AS16: 6500 | AT16: 6500 | AU16: 6500 | AV16: 6500 | AW16: 6500 | AX16: =IF(COUNT($AL16:$AW16)=0,"",SUM($AL16:$AW16)) -> 72000 | AY16: =IF($AX16="","",$AX16-IF($W16="",0,$W16)) -> 46400 | AZ16: =IF($AX16="","",$AX16-IF($AK16="",0,$AK16)) -> 38394.21 | BA16: AUMENTO DE VOLUME DE UTILIZAÇÃO PARA DISPAROS E ATENDIMENTO CHATBOT - ENTRADA DO VAREJO - Aumento de valores cambiais da Meta. | BB16: Rascunho
A17: =IF(OR($B17="",$D17="",$G17=""),"",ROW()-7) -> 10 | B17: ECEL COMERCIALIZADORA | C17: =IF($B17="","",IFERROR(INDEX(Apoio!$L$3:$L$81,MATCH($B17,Apoio!$K$3:$K$81,0)),"")) -> COMERCIALIZADORA | D17: C104 | E17: =IF($D17="","",IFERROR(INDEX(Apoio!$C$3:$C$81,MATCH($D17,Apoio!$B$3:$B$81,0)),"")) -> TI | F17: =IF($D17="","",IFERROR(INDEX(Apoio!$D$3:$D$81,MATCH($D17,Apoio!$B$3:$B$81,0)),"")) -> Marcelo Bronzatti | G17: =IF($H17="","",IFERROR(_xlfn.XLOOKUP(H17,'De x Para DRE'!C:C,'De x Para DRE'!B:B),"")) -> 5110100702 | H17: SISTEMAS DE GESTÃO ADM/OPERACIONAL | I17: =IF($G17="","",IFERROR(INDEX('De x Para DRE'!$E$3:$E$210,MATCH($G17,'De x Para DRE'!$B$3:$B$210,0)),"")) -> 3.1 G&A | J17: ARPSist - Sistema | K17: 1380 | L17: 1380 | M17: 1380 | N17: 1380 | O17: 1380 | P17: 1380 | Q17: 1449 | R17: 1449 | S17: 1449 | T17: 1449 | U17: 1449 | V17: 1449 | W17: =SUM(K17:V17) -> 16974 | X17: 1380 | Y17: 1380 | Z17: 1380 | AA17: 1380 | AB17: 1380 | AC17: 1560 | AD17: 1560 | AE17: 1560 | AF17: 1560 | AG17: 1560 | AH17: 1560 | AI17: 1560 | AJ17: =SUM(X17:AE17) -> 11580 | AK17: =SUM(X17:AI17) -> 17820 | AL17: 1300 | AM17: 1300 | AN17: 1300 | AO17: 1300 | AP17: 1300 | AQ17: 1300 | AR17: 1300 | AS17: 1300 | AT17: 1300 | AU17: 1300 | AV17: 1300 | AW17: 1300 | AX17: =IF(COUNT($AL17:$AW17)=0,"",SUM($AL17:$AW17)) -> 15600 | AY17: =IF($AX17="","",$AX17-IF($W17="",0,$W17)) -> -1374 | AZ17: =IF($AX17="","",$AX17-IF($AK17="",0,$AK17)) -> -2220 | BA17: NEGOCIADO REDUÇÃO DE VLR PARA 4HS + 1 ALUGUEL DO MR44 | BB17: Rascunho
A18: =IF(OR($B18="",$D18="",$G18=""),"",ROW()-7) -> 11 | B18: ECEL COMERCIALIZADORA | C18: =IF($B18="","",IFERROR(INDEX(Apoio!$L$3:$L$81,MATCH($B18,Apoio!$K$3:$K$81,0)),"")) -> COMERCIALIZADORA | D18: C104 | E18: =IF($D18="","",IFERROR(INDEX(Apoio!$C$3:$C$81,MATCH($D18,Apoio!$B$3:$B$81,0)),"")) -> TI | F18: =IF($D18="","",IFERROR(INDEX(Apoio!$D$3:$D$81,MATCH($D18,Apoio!$B$3:$B$81,0)),"")) -> Marcelo Bronzatti | G18: =IF($H18="","",IFERROR(_xlfn.XLOOKUP(H18,'De x Para DRE'!C:C,'De x Para DRE'!B:B),"")) -> 5110100702 | H18: SISTEMAS DE GESTÃO ADM/OPERACIONAL | I18: =IF($G18="","",IFERROR(INDEX('De x Para DRE'!$E$3:$E$210,MATCH($G18,'De x Para DRE'!$B$3:$B$210,0)),"")) -> 3.1 G&A | J18: AKSum IT - Sistema | K18: 495.31 | L18: 495.31 | M18: 495.31 | N18: 495.31 | O18: 495.31 | P18: 495.31 | Q18: 520.0755 | R18: 520.0755 | S18: 520.0755 | T18: 520.0755 | U18: 520.0755 | V18: 520.0755 | W18: =SUM(K18:V18) -> 6092.313 | X18: 495.31 | Y18: 495.31 | Z18: =495.31 -> 495.31 | AA18: 495.31 | AB18: 495.31 | AC18: 495.31 | AD18: 495.31 | AE18: 495.31 | AF18: 495.31 | AG18: 495.31 | AH18: 495.31 | AI18: 495.31 | AJ18: =SUM(X18:AE18) -> 3962.48 | AK18: =SUM(X18:AI18) -> 5943.72 | AL18: 0 | AM18: 0 | AN18: 0 | AO18: 0 | AP18: 0 | AQ18: 0 | AR18: 0 | AS18: 0 | AT18: 0 | AU18: 0 | AV18: 0 | AW18: 0 | AX18: =IF(COUNT($AL18:$AW18)=0,"",SUM($AL18:$AW18)) -> 0 | AY18: =IF($AX18="","",$AX18-IF($W18="",0,$W18)) -> -6092.313 | AZ18: =IF($AX18="","",$AX18-IF($AK18="",0,$AK18)) -> -5943.72 | BA18: R$ 836,64 + O365 [101 usu *148,71] | BB18: Rascunho
A19: =IF(OR($B19="",$D19="",$G19=""),"",ROW()-7) -> 12 | B19: ECEL COMERCIALIZADORA | C19: =IF($B19="","",IFERROR(INDEX(Apoio!$L$3:$L$81,MATCH($B19,Apoio!$K$3:$K$81,0)),"")) -> COMERCIALIZADORA | D19: C104 | E19: =IF($D19="","",IFERROR(INDEX(Apoio!$C$3:$C$81,MATCH($D19,Apoio!$B$3:$B$81,0)),"")) -> TI | F19: =IF($D19="","",IFERROR(INDEX(Apoio!$D$3:$D$81,MATCH($D19,Apoio!$B$3:$B$81,0)),"")) -> Marcelo Bronzatti | G19: =IF($H19="","",IFERROR(_xlfn.XLOOKUP(H19,'De x Para DRE'!C:C,'De x Para DRE'!B:B),"")) -> 5110100702 | H19: SISTEMAS DE GESTÃO ADM/OPERACIONAL | I19: =IF($G19="","",IFERROR(INDEX('De x Para DRE'!$E$3:$E$210,MATCH($G19,'De x Para DRE'!$B$3:$B$210,0)),"")) -> 3.1 G&A | J19: Imagine - Sistema Portal de Compras | W19: =SUM(K19:V19) -> 0 | AB19: 3800 | AC19: =2500+1300 -> 3800 | AD19: 3800 | AE19: 3800 | AF19: 3800 | AG19: 3800 | AH19: 3800 | AI19: 3800 | AJ19: =SUM(X19:AE19) -> 15200 | AK19: =SUM(X19:AI19) -> 30400 | AL19: 1300 | AM19: 1300 | AN19: 1300 | AO19: 1300 | AP19: 1500 | AQ19: 1500 | AR19: 1500 | AS19: 1500 | AT19: 1500 | AU19: 1500 | AV19: 1500 | AW19: 1500 | AX19: =IF(COUNT($AL19:$AW19)=0,"",SUM($AL19:$AW19)) -> 17200 | AY19: =IF($AX19="","",$AX19-IF($W19="",0,$W19)) -> 17200 | AZ19: =IF($AX19="","",$AX19-IF($AK19="",0,$AK19)) -> -13200 | BA19: REAJUSTE IGPM | BB19: Rascunho
A20: =IF(OR($B20="",$D20="",$G20=""),"",ROW()-7) -> 13 | B20: ECEL COMERCIALIZADORA | C20: =IF($B20="","",IFERROR(INDEX(Apoio!$L$3:$L$81,MATCH($B20,Apoio!$K$3:$K$81,0)),"")) -> COMERCIALIZADORA | D20: C104 | E20: =IF($D20="","",IFERROR(INDEX(Apoio!$C$3:$C$81,MATCH($D20,Apoio!$B$3:$B$81,0)),"")) -> TI | F20: =IF($D20="","",IFERROR(INDEX(Apoio!$D$3:$D$81,MATCH($D20,Apoio!$B$3:$B$81,0)),"")) -> Marcelo Bronzatti | G20: =IF($H20="","",IFERROR(_xlfn.XLOOKUP(H20,'De x Para DRE'!C:C,'De x Para DRE'!B:B),"")) -> 5110100702 | H20: SISTEMAS DE GESTÃO ADM/OPERACIONAL | I20: =IF($G20="","",IFERROR(INDEX('De x Para DRE'!$E$3:$E$210,MATCH($G20,'De x Para DRE'!$B$3:$B$210,0)),"")) -> 3.1 G&A | J20: SouCloud - Licenças Office | K20: 21967.74 | L20: 21967.74 | M20: 21967.74 | N20: 21967.74 | O20: 21967.74 | P20: 19967.74 | Q20: 19967.74 | R20: 19967.74 | S20: 19967.74 | T20: 17600 | U20: 17600 | V20: 17600 | W20: =SUM(K20:V20) -> 242509.66 | X20: 21967.74 | Y20: 21967.74 | Z20: 21967.74 | AA20: 21967.74 | AB20: 21967.74 | AC20: 21967.74 | AD20: 21967.74 | AE20: 22020.29 | AF20: 22020.29 | AG20: 22020.29 | AH20: 22020.29 | AI20: 22020.29 | AJ20: =SUM(X20:AE20) -> 175794.47 | AK20: =SUM(X20:AI20) -> 263875.63 | AL20: 16000 | AM20: 16000 | AN20: 16000 | AO20: 16000 | AP20: 16000 | AQ20: 16000 | AR20: 16000 | AS20: 16000 | AT20: 16000 | AU20: 18000 | AV20: 18000 | AW20: 18000 | AX20: =IF(COUNT($AL20:$AW20)=0,"",SUM($AL20:$AW20)) -> 198000 | AY20: =IF($AX20="","",$AX20-IF($W20="",0,$W20)) -> -44509.66 | AZ20: =IF($AX20="","",$AX20-IF($AK20="",0,$AK20)) -> -65875.63 | BA20: SUBS MENSAL S/FIDELIDADE | BB20: Rascunho
A21: =IF(OR($B21="",$D21="",$G21=""),"",ROW()-7) -> 14 | B21: ECEL COMERCIALIZADORA | C21: =IF($B21="","",IFERROR(INDEX(Apoio!$L$3:$L$81,MATCH($B21,Apoio!$K$3:$K$81,0)),"")) -> COMERCIALIZADORA | D21: C104 | E21: =IF($D21="","",IFERROR(INDEX(Apoio!$C$3:$C$81,MATCH($D21,Apoio!$B$3:$B$81,0)),"")) -> TI | F21: =IF($D21="","",IFERROR(INDEX(Apoio!$D$3:$D$81,MATCH($D21,Apoio!$B$3:$B$81,0)),"")) -> Marcelo Bronzatti | G21: =IF($H21="","",IFERROR(_xlfn.XLOOKUP(H21,'De x Para DRE'!C:C,'De x Para DRE'!B:B),"")) -> 5110100702 | H21: SISTEMAS DE GESTÃO ADM/OPERACIONAL | I21: =IF($G21="","",IFERROR(INDEX('De x Para DRE'!$E$3:$E$210,MATCH($G21,'De x Para DRE'!$B$3:$B$210,0)),"")) -> 3.1 G&A | J21: TiqueTaque - Sistema Ponto RH | K21: 605 | L21: 605 | M21: 605 | N21: 605 | O21: 605 | P21: 605 | Q21: 605 | R21: 605 | S21: 605 | T21: 605 | U21: 605 | V21: 605 | W21: =SUM(K21:V21) -> 7260 | Y21: 605.33 | Z21: 605.33 | AA21: 432.59 | AB21: 432.59 | AC21: 432.59 | AD21: 432.59 | AE21: 432.59 | AF21: 432.59 | AG21: 432.59 | AH21: 432.59 | AI21: 432.59 | AJ21: =SUM(X21:AE21) -> 3373.61 | AK21: =SUM(X21:AI21) -> 5103.97 | AL21: 500 | AM21: 500 | AN21: 500 | AO21: 500 | AP21: 500 | AQ21: 500 | AR21: 500 | AS21: 500 | AT21: 500 | AU21: 500 | AV21: 500 | AW21: 500 | AX21: =IF(COUNT($AL21:$AW21)=0,"",SUM($AL21:$AW21)) -> 6000 | AY21: =IF($AX21="","",$AX21-IF($W21="",0,$W21)) -> -1260 | AZ21: =IF($AX21="","",$AX21-IF($AK21="",0,$AK21)) -> 896.03 | BB21: Rascunho
A22: =IF(OR($B22="",$D22="",$G22=""),"",ROW()-7) -> 15 | B22: ECEL COMERCIALIZADORA | C22: =IF($B22="","",IFERROR(INDEX(Apoio!$L$3:$L$81,MATCH($B22,Apoio!$K$3:$K$81,0)),"")) -> COMERCIALIZADORA | D22: C104 | E22: =IF($D22="","",IFERROR(INDEX(Apoio!$C$3:$C$81,MATCH($D22,Apoio!$B$3:$B$81,0)),"")) -> TI | F22: =IF($D22="","",IFERROR(INDEX(Apoio!$D$3:$D$81,MATCH($D22,Apoio!$B$3:$B$81,0)),"")) -> Marcelo Bronzatti | G22: =IF($H22="","",IFERROR(_xlfn.XLOOKUP(H22,'De x Para DRE'!C:C,'De x Para DRE'!B:B),"")) -> 5110100702 | H22: SISTEMAS DE GESTÃO ADM/OPERACIONAL | I22: =IF($G22="","",IFERROR(INDEX('De x Para DRE'!$E$3:$E$210,MATCH($G22,'De x Para DRE'!$B$3:$B$210,0)),"")) -> 3.1 G&A | J22: Infinity Soluções - Sistema 4Expenses | W22: =SUM(K22:V22) -> 0 | AB22: 1800 | AC22: =1800+2500.2 -> 4300.2 | AD22: =1800+2500.2 -> 4300.2 | AE22: 0 | AF22: 0 | AG22: 0 | AH22: 0 | AI22: 0 | AJ22: =SUM(X22:AE22) -> 10400.4 | AK22: =SUM(X22:AI22) -> 10400.4 | AL22: 0 | AM22: 0 | AN22: 0 | AO22: 0 | AP22: 0 | AQ22: 0 | AR22: 0 | AS22: 0 | AT22: 0 | AU22: 0 | AV22: 0 | AW22: 0 | AX22: =IF(COUNT($AL22:$AW22)=0,"",SUM($AL22:$AW22)) -> 0 | AY22: =IF($AX22="","",$AX22-IF($W22="",0,$W22)) -> 0 | AZ22: =IF($AX22="","",$AX22-IF($AK22="",0,$AK22)) -> -10400.4 | BB22: Rascunho
A23: =IF(OR($B23="",$D23="",$G23=""),"",ROW()-7) -> 16 | B23: ECEL COMERCIALIZADORA | C23: =IF($B23="","",IFERROR(INDEX(Apoio!$L$3:$L$81,MATCH($B23,Apoio!$K$3:$K$81,0)),"")) -> COMERCIALIZADORA | D23: C104 | E23: =IF($D23="","",IFERROR(INDEX(Apoio!$C$3:$C$81,MATCH($D23,Apoio!$B$3:$B$81,0)),"")) -> TI | F23: =IF($D23="","",IFERROR(INDEX(Apoio!$D$3:$D$81,MATCH($D23,Apoio!$B$3:$B$81,0)),"")) -> Marcelo Bronzatti | G23: =IF($H23="","",IFERROR(_xlfn.XLOOKUP(H23,'De x Para DRE'!C:C,'De x Para DRE'!B:B),"")) -> 5110100704 | H23: DESPESA TELEFONIA FIXA E MÓVEL | I23: =IF($G23="","",IFERROR(INDEX('De x Para DRE'!$E$3:$E$210,MATCH($G23,'De x Para DRE'!$B$3:$B$210,0)),"")) -> 3.1 G&A | J23: Signallink (SUBS POR SURFIX) | K23: 350 | L23: 350 | M23: 350 | N23: 350 | O23: 350 | P23: 350 | Q23: 367.5 | R23: 367.5 | S23: 367.5 | T23: 367.5 | U23: 367.5 | V23: 367.5 | W23: =SUM(K23:V23) -> 4305 | X23: 321.6 | Y23: 328.35 | Z23: 321.6 | AA23: 328.14 | AB23: =321.6 -> 321.6 | AC23: 321.6 | AD23: 396.6 | AE23: 357.14833 | AF23: 357.14833 | AG23: 357.14833 | AH23: 357.14833 | AI23: 357.14833 | AJ23: =SUM(X23:AE23) -> 2696.6383 | AK23: =SUM(X23:AI23) -> 4125.2317 | AL23: 0 | AM23: 0 | AN23: 0 | AO23: 0 | AP23: 0 | AQ23: 0 | AR23: 0 | AS23: 0 | AT23: 0 | AU23: 0 | AV23: 0 | AW23: 0 | AX23: =IF(COUNT($AL23:$AW23)=0,"",SUM($AL23:$AW23)) -> 0 | AY23: =IF($AX23="","",$AX23-IF($W23="",0,$W23)) -> -4305 | AZ23: =IF($AX23="","",$AX23-IF($AK23="",0,$AK23)) -> -4125.2317 | BB23: Rascunho
A24: =IF(OR($B24="",$D24="",$G24=""),"",ROW()-7) -> 17 | B24: ECEL COMERCIALIZADORA | C24: =IF($B24="","",IFERROR(INDEX(Apoio!$L$3:$L$81,MATCH($B24,Apoio!$K$3:$K$81,0)),"")) -> COMERCIALIZADORA | D24: C104 | E24: =IF($D24="","",IFERROR(INDEX(Apoio!$C$3:$C$81,MATCH($D24,Apoio!$B$3:$B$81,0)),"")) -> TI | F24: =IF($D24="","",IFERROR(INDEX(Apoio!$D$3:$D$81,MATCH($D24,Apoio!$B$3:$B$81,0)),"")) -> Marcelo Bronzatti | G24: =IF($H24="","",IFERROR(_xlfn.XLOOKUP(H24,'De x Para DRE'!C:C,'De x Para DRE'!B:B),"")) -> 5110100704 | H24: DESPESA TELEFONIA FIXA E MÓVEL | I24: =IF($G24="","",IFERROR(INDEX('De x Para DRE'!$E$3:$E$210,MATCH($G24,'De x Para DRE'!$B$3:$B$210,0)),"")) -> 3.1 G&A | J24: TIM - Celulares Corporativos / ( SUBST VIVO CELULAR) | K24: 6600 | L24: 6600 | M24: 7500 | N24: 5000 | O24: 5000 | P24: 5000 | Q24: 5000 | R24: 5000 | S24: 5000 | T24: 5000 | U24: 5000 | V24: 5000 | W24: =SUM(K24:V24) -> 65700 | X24: 6279.47 | Y24: =6380.8-566.99 -> 5813.81 | Z24: 6466.62 | AA24: 3878.18 | AB24: 3759.55 | AC24: 3762.99 | AD24: 4131.83 | AE24: 4311.4 | AF24: 3800.24 | AG24: 3800.24 | AH24: 3800.24 | AI24: 3800.24 | AJ24: =SUM(X24:AE24) -> 38403.85 | AK24: =SUM(X24:AI24) -> 53604.81 | AL24: 3400 | AM24: 3400 | AN24: 3400 | AO24: 3400 | AP24: 3400 | AQ24: 3400 | AR24: 3400 | AS24: 3400 | AT24: 3400 | AU24: 3400 | AV24: 3400 | AW24: 3400 | AX24: =IF(COUNT($AL24:$AW24)=0,"",SUM($AL24:$AW24)) -> 40800 | AY24: =IF($AX24="","",$AX24-IF($W24="",0,$W24)) -> -24900 | AZ24: =IF($AX24="","",$AX24-IF($AK24="",0,$AK24)) -> -12804.81 | BA24: 69 LINHAS * 49,00 | BB24: Rascunho
A25: =IF(OR($B25="",$D25="",$G25=""),"",ROW()-7) -> 18 | B25: ECEL COMERCIALIZADORA | C25: =IF($B25="","",IFERROR(INDEX(Apoio!$L$3:$L$81,MATCH($B25,Apoio!$K$3:$K$81,0)),"")) -> COMERCIALIZADORA | D25: C104 | E25: =IF($D25="","",IFERROR(INDEX(Apoio!$C$3:$C$81,MATCH($D25,Apoio!$B$3:$B$81,0)),"")) -> TI | F25: =IF($D25="","",IFERROR(INDEX(Apoio!$D$3:$D$81,MATCH($D25,Apoio!$B$3:$B$81,0)),"")) -> Marcelo Bronzatti | G25: =IF($H25="","",IFERROR(_xlfn.XLOOKUP(H25,'De x Para DRE'!C:C,'De x Para DRE'!B:B),"")) -> 5110100704 | H25: DESPESA TELEFONIA FIXA E MÓVEL | I25: =IF($G25="","",IFERROR(INDEX('De x Para DRE'!$E$3:$E$210,MATCH($G25,'De x Para DRE'!$B$3:$B$210,0)),"")) -> 3.1 G&A | J25: VIVO - VOIP / A2M TECNOLOGIA EM INTERNET LTDA (SURFIX) | K25: 2438 | L25: 2438 | M25: 2438 | N25: 2438 | O25: 2438 | P25: 2438 | Q25: 2438 | R25: 2438 | S25: 2438 | T25: 2438 | U25: 1000 | V25: 1000 | W25: =SUM(K25:V25) -> 26380 | X25: 2871.33 | Y25: 2855.78 | Z25: 3599.63 | AA25: 4248.26 | AB25: 3955.2 | AC25: 4811.11 | AD25: =1462.02+975.95 -> 2437.97 | AE25: 3884.79 | AF25: 3723.5517 | AG25: 3723.5517 | AH25: 3723.5517 | AI25: 3723.5517 | AJ25: =SUM(X25:AE25) -> 28664.07 | AK25: =SUM(X25:AI25) -> 43558.277 | AL25: 700 | AM25: 700 | AN25: 700 | AO25: 700 | AP25: 700 | AQ25: 700 | AR25: 730 | AS25: 730 | AT25: 730 | AU25: 730 | AV25: 730 | AW25: 730 | AX25: =IF(COUNT($AL25:$AW25)=0,"",SUM($AL25:$AW25)) -> 8580 | AY25: =IF($AX25="","",$AX25-IF($W25="",0,$W25)) -> -17800 | AZ25: =IF($AX25="","",$AX25-IF($AK25="",0,$AK25)) -> -34978.277 | BA25: 15 LINHAS - SERVICO DE TELEFONIA DID 1 CANAL - R$ 15,00 - TOTAL R$ 225,00 01 CENTRAL DE COMUNICAÇÃO CLOUD PABX/IP COM 4 CANAIS SIMULTÂNEOS - R$ 439,00 | BB25: Rascunho
A26: =IF(OR($B26="",$D26="",$G26=""),"",ROW()-7) -> 19 | B26: ECEL COMERCIALIZADORA | C26: =IF($B26="","",IFERROR(INDEX(Apoio!$L$3:$L$81,MATCH($B26,Apoio!$K$3:$K$81,0)),"")) -> COMERCIALIZADORA | D26: C104 | E26: =IF($D26="","",IFERROR(INDEX(Apoio!$C$3:$C$81,MATCH($D26,Apoio!$B$3:$B$81,0)),"")) -> TI | F26: =IF($D26="","",IFERROR(INDEX(Apoio!$D$3:$D$81,MATCH($D26,Apoio!$B$3:$B$81,0)),"")) -> Marcelo Bronzatti | G26: =IF($H26="","",IFERROR(_xlfn.XLOOKUP(H26,'De x Para DRE'!C:C,'De x Para DRE'!B:B),"")) -> 5110100705 | H26: DESPESA COMUNICAÇÃO DE DADOS | I26: =IF($G26="","",IFERROR(INDEX('De x Para DRE'!$E$3:$E$210,MATCH($G26,'De x Para DRE'!$B$3:$B$210,0)),"")) -> 3.1 G&A | J26: CLARO - Redundância Internet Recife | K26: 176 | L26: 176 | M26: 176 | N26: 176 | O26: 200 | P26: 200 | Q26: 200 | R26: 200 | S26: 200 | T26: 200 | U26: 200 | V26: 200 | W26: =SUM(K26:V26) -> 2304 | X26: 146.78 | Y26: 192.63 | Z26: 189.59 | AA26: 189.59 | AB26: 189.59 | AC26: 189.59 | AD26: 189.59 | AE26: 189.59 | AF26: 189.59 | AG26: 189.59 | AH26: 189.59 | AI26: 189.59 | AJ26: =SUM(X26:AE26) -> 1476.95 | AK26: =SUM(X26:AI26) -> 2235.31 | AL26: 200 | AM26: 200 | AN26: 200 | AO26: 200 | AP26: 200 | AQ26: 200 | AR26: 200 | AS26: 200 | AT26: 200 | AU26: 200 | AV26: 200 | AW26: 200 | AX26: =IF(COUNT($AL26:$AW26)=0,"",SUM($AL26:$AW26)) -> 2400 | AY26: =IF($AX26="","",$AX26-IF($W26="",0,$W26)) -> 96 | AZ26: =IF($AX26="","",$AX26-IF($AK26="",0,$AK26)) -> 164.69 | BB26: Rascunho
A27: =IF(OR($B27="",$D27="",$G27=""),"",ROW()-7) -> 20 | B27: ECEL COMERCIALIZADORA | C27: =IF($B27="","",IFERROR(INDEX(Apoio!$L$3:$L$81,MATCH($B27,Apoio!$K$3:$K$81,0)),"")) -> COMERCIALIZADORA | D27: C104 | E27: =IF($D27="","",IFERROR(INDEX(Apoio!$C$3:$C$81,MATCH($D27,Apoio!$B$3:$B$81,0)),"")) -> TI | F27: =IF($D27="","",IFERROR(INDEX(Apoio!$D$3:$D$81,MATCH($D27,Apoio!$B$3:$B$81,0)),"")) -> Marcelo Bronzatti | G27: =IF($H27="","",IFERROR(_xlfn.XLOOKUP(H27,'De x Para DRE'!C:C,'De x Para DRE'!B:B),"")) -> 5110100705 | H27: DESPESA COMUNICAÇÃO DE DADOS | I27: =IF($G27="","",IFERROR(INDEX('De x Para DRE'!$E$3:$E$210,MATCH($G27,'De x Para DRE'!$B$3:$B$210,0)),"")) -> 3.1 G&A | J27: WRL Connect | W27: =SUM(K27:V27) -> 0 | X27: =1201.43+1241.48 -> 2442.91 | Y27: =1241.48*2 -> 2482.96 | AD27: 0 | AE27: 0 | AF27: 0 | AG27: 0 | AH27: 0 | AI27: 0 | AJ27: =SUM(X27:AE27) -> 4925.87 | AK27: =SUM(X27:AI27) -> 4925.87 | AL27: 0 | AM27: 0 | AN27: 0 | AO27: 0 | AP27: 0 | AQ27: 0 | AR27: 0 | AS27: 0 | AT27: 0 | AU27: 0 | AV27: 0 | AW27: 0 | AX27: =IF(COUNT($AL27:$AW27)=0,"",SUM($AL27:$AW27)) -> 0 | AY27: =IF($AX27="","",$AX27-IF($W27="",0,$W27)) -> 0 | AZ27: =IF($AX27="","",$AX27-IF($AK27="",0,$AK27)) -> -4925.87 | BB27: Rascunho
A28: =IF(OR($B28="",$D28="",$G28=""),"",ROW()-7) -> 21 | B28: ECEL COMERCIALIZADORA | C28: =IF($B28="","",IFERROR(INDEX(Apoio!$L$3:$L$81,MATCH($B28,Apoio!$K$3:$K$81,0)),"")) -> COMERCIALIZADORA | D28: C104 | E28: =IF($D28="","",IFERROR(INDEX(Apoio!$C$3:$C$81,MATCH($D28,Apoio!$B$3:$B$81,0)),"")) -> TI | F28: =IF($D28="","",IFERROR(INDEX(Apoio!$D$3:$D$81,MATCH($D28,Apoio!$B$3:$B$81,0)),"")) -> Marcelo Bronzatti | G28: =IF($H28="","",IFERROR(_xlfn.XLOOKUP(H28,'De x Para DRE'!C:C,'De x Para DRE'!B:B),"")) -> 5110100705 | H28: DESPESA COMUNICAÇÃO DE DADOS | I28: =IF($G28="","",IFERROR(INDEX('De x Para DRE'!$E$3:$E$210,MATCH($G28,'De x Para DRE'!$B$3:$B$210,0)),"")) -> 3.1 G&A | J28: CLDS Cloud/Mundivox - Internet Recife | K28: 2750 | L28: 2750 | M28: 2750 | N28: 2750 | O28: 2750 | P28: 2750 | Q28: 2750 | R28: 2750 | S28: 2750 | T28: 2750 | U28: 2750 | V28: 2750 | W28: =SUM(K28:V28) -> 33000 | X28: 1201.43 | Y28: =1500+1480.5 -> 2980.5 | Z28: =680.81+1241.48+1500 -> 3422.29 | AA28: 2741.48 | AB28: 2741.48 | AC28: 2741.48 | AD28: 2741.48 | AE28: 2741.48 | AF28: 2741.48 | AG28: 2741.48 | AH28: 2741.48 | AI28: 2741.48 | AJ28: =SUM(X28:AE28) -> 21311.62 | AK28: =SUM(X28:AI28) -> 32277.54 | AL28: 2741 | AM28: 2741 | AN28: 2741 | AO28: 2741 | AP28: 2741 | AQ28: 2741 | AR28: 2741 | AS28: 2741 | AT28: 2741 | AU28: 2741 | AV28: 2741 | AW28: 2741 | AX28: =IF(COUNT($AL28:$AW28)=0,"",SUM($AL28:$AW28)) -> 32892 | AY28: =IF($AX28="","",$AX28-IF($W28="",0,$W28)) -> -108 | AZ28: =IF($AX28="","",$AX28-IF($AK28="",0,$AK28)) -> 614.46 | BB28: Rascunho
A29: =IF(OR($B29="",$D29="",$G29=""),"",ROW()-7) -> 22 | B29: ECEL COMERCIALIZADORA | C29: =IF($B29="","",IFERROR(INDEX(Apoio!$L$3:$L$81,MATCH($B29,Apoio!$K$3:$K$81,0)),"")) -> COMERCIALIZADORA | D29: C104 | E29: =IF($D29="","",IFERROR(INDEX(Apoio!$C$3:$C$81,MATCH($D29,Apoio!$B$3:$B$81,0)),"")) -> TI | F29: =IF($D29="","",IFERROR(INDEX(Apoio!$D$3:$D$81,MATCH($D29,Apoio!$B$3:$B$81,0)),"")) -> Marcelo Bronzatti | G29: =IF($H29="","",IFERROR(_xlfn.XLOOKUP(H29,'De x Para DRE'!C:C,'De x Para DRE'!B:B),"")) -> 5110100705 | H29: DESPESA COMUNICAÇÃO DE DADOS | I29: =IF($G29="","",IFERROR(INDEX('De x Para DRE'!$E$3:$E$210,MATCH($G29,'De x Para DRE'!$B$3:$B$210,0)),"")) -> 3.1 G&A | J29: SantoDigital - Google | K29: 60 | L29: 60 | M29: 60 | N29: 60 | O29: 400 | P29: 400 | Q29: 400 | R29: 400 | S29: 400 | T29: 400 | U29: 400 | V29: 400 | W29: =SUM(K29:V29) -> 3440 | X29: 54.39 | Y29: 66.75 | Z29: 35.41 | AA29: 37.01 | AB29: =357.42 -> 357.42 | AC29: =359.48 -> 359.48 | AD29: 489.36 | AE29: 743.5 | AF29: 359.48 | AG29: 359.48 | AH29: 359.48 | AI29: 359.48 | AJ29: =SUM(X29:AE29) -> 2143.32 | AK29: =SUM(X29:AI29) -> 3581.24 | AL29: 1500 | AM29: 1500 | AN29: 1500 | AO29: 1500 | AP29: 1500 | AQ29: 1500 | AR29: 1500 | AS29: 1500 | AT29: 1500 | AU29: 1500 | AV29: 1500 | AW29: 1500 | AX29: =IF(COUNT($AL29:$AW29)=0,"",SUM($AL29:$AW29)) -> 18000 | AY29: =IF($AX29="","",$AX29-IF($W29="",0,$W29)) -> 14560 | AZ29: =IF($AX29="","",$AX29-IF($AK29="",0,$AK29)) -> 14418.76 | BB29: Rascunho
A30: =IF(OR($B30="",$D30="",$G30=""),"",ROW()-7) -> 23 | B30: ECEL COMERCIALIZADORA | C30: =IF($B30="","",IFERROR(INDEX(Apoio!$L$3:$L$81,MATCH($B30,Apoio!$K$3:$K$81,0)),"")) -> COMERCIALIZADORA | D30: C104 | E30: =IF($D30="","",IFERROR(INDEX(Apoio!$C$3:$C$81,MATCH($D30,Apoio!$B$3:$B$81,0)),"")) -> TI | F30: =IF($D30="","",IFERROR(INDEX(Apoio!$D$3:$D$81,MATCH($D30,Apoio!$B$3:$B$81,0)),"")) -> Marcelo Bronzatti | G30: =IF($H30="","",IFERROR(_xlfn.XLOOKUP(H30,'De x Para DRE'!C:C,'De x Para DRE'!B:B),"")) -> 5110100803 | H30: DESPESA COM HOSPEDAGEM | I30: =IF($G30="","",IFERROR(INDEX('De x Para DRE'!$E$3:$E$210,MATCH($G30,'De x Para DRE'!$B$3:$B$210,0)),"")) -> 3.1 G&A | J30: Hospedagens | K30: 240.73875 | L30: 240.73875 | M30: 240.73875 | N30: 240.73875 | O30: 240.73875 | P30: 240.73875 | Q30: 240.73875 | R30: 240.73875 | S30: 240.73875 | T30: 240.73875 | U30: 240.73875 | V30: 240.73875 | W30: =SUM(K30:V30) -> 2888.865 | X30: 0 | Y30: 1116.15 | Z30: 2370.4 | AA30: 0 | AB30: 0 | AC30: 0 | AD30: 0 | AE30: 0 | AF30: 0 | AG30: 0 | AH30: 0 | AI30: 0 | AJ30: =SUM(X30:AE30) -> 3486.55 | AK30: =SUM(X30:AI30) -> 3486.55 | AL30: 500 | AM30: 500 | AN30: 500 | AO30: 500 | AP30: 500 | AQ30: 500 | AR30: 500 | AS30: 500 | AT30: 500 | AU30: 500 | AV30: 500 | AW30: 500 | AX30: =IF(COUNT($AL30:$AW30)=0,"",SUM($AL30:$AW30)) -> 6000 | AY30: =IF($AX30="","",$AX30-IF($W30="",0,$W30)) -> 3111.135 | AZ30: =IF($AX30="","",$AX30-IF($AK30="",0,$AK30)) -> 2513.45 | BB30: Rascunho
A31: =IF(OR($B31="",$D31="",$G31=""),"",ROW()-7) -> 24 | B31: ECEL COMERCIALIZADORA | C31: =IF($B31="","",IFERROR(INDEX(Apoio!$L$3:$L$81,MATCH($B31,Apoio!$K$3:$K$81,0)),"")) -> COMERCIALIZADORA | D31: C104 | E31: =IF($D31="","",IFERROR(INDEX(Apoio!$C$3:$C$81,MATCH($D31,Apoio!$B$3:$B$81,0)),"")) -> TI | F31: =IF($D31="","",IFERROR(INDEX(Apoio!$D$3:$D$81,MATCH($D31,Apoio!$B$3:$B$81,0)),"")) -> Marcelo Bronzatti | G31: =IF($H31="","",IFERROR(_xlfn.XLOOKUP(H31,'De x Para DRE'!C:C,'De x Para DRE'!B:B),"")) -> 5110100804 | H31: DESPESA COM PASSAGENS | I31: =IF($G31="","",IFERROR(INDEX('De x Para DRE'!$E$3:$E$210,MATCH($G31,'De x Para DRE'!$B$3:$B$210,0)),"")) -> 3.1 G&A | J31: Passagens | K31: 737.79 | L31: 737.79 | M31: 737.79 | N31: 737.79 | O31: 737.79 | P31: 737.79 | Q31: 737.79 | R31: 737.79 | S31: 737.79 | T31: 737.79 | U31: 737.79 | V31: 737.79 | W31: =SUM(K31:V31) -> 8853.48 | X31: 2923.11 | Y31: 1418.42 | Z31: 3915.02 | AA31: 0 | AB31: 0 | AC31: 0 | AD31: 0 | AE31: 0 | AF31: 0 | AG31: 0 | AH31: 0 | AI31: 0 | AJ31: =SUM(X31:AE31) -> 8256.55 | AK31: =SUM(X31:AI31) -> 8256.55 | AL31: 600 | AM31: 600 | AN31: 600 | AO31: 600 | AP31: 600 | AQ31: 600 | AR31: 600 | AS31: 600 | AT31: 600 | AU31: 600 | AV31: 600 | AW31: 600 | AX31: =IF(COUNT($AL31:$AW31)=0,"",SUM($AL31:$AW31)) -> 7200 | AY31: =IF($AX31="","",$AX31-IF($W31="",0,$W31)) -> -1653.48 | AZ31: =IF($AX31="","",$AX31-IF($AK31="",0,$AK31)) -> -1056.55 | BB31: Rascunho
A32: =IF(OR($B32="",$D32="",$G32=""),"",ROW()-7) -> 25 | B32: ECEL COMERCIALIZADORA | C32: =IF($B32="","",IFERROR(INDEX(Apoio!$L$3:$L$81,MATCH($B32,Apoio!$K$3:$K$81,0)),"")) -> COMERCIALIZADORA | D32: C104 | E32: =IF($D32="","",IFERROR(INDEX(Apoio!$C$3:$C$81,MATCH($D32,Apoio!$B$3:$B$81,0)),"")) -> TI | F32: =IF($D32="","",IFERROR(INDEX(Apoio!$D$3:$D$81,MATCH($D32,Apoio!$B$3:$B$81,0)),"")) -> Marcelo Bronzatti | G32: =IF($H32="","",IFERROR(_xlfn.XLOOKUP(H32,'De x Para DRE'!C:C,'De x Para DRE'!B:B),"")) -> 5110100917 | H32: DESPESA COMBUST./LUBRIF. VEÍCULOS | I32: =IF($G32="","",IFERROR(INDEX('De x Para DRE'!$E$3:$E$210,MATCH($G32,'De x Para DRE'!$B$3:$B$210,0)),"")) -> 3.1 G&A | J32: Combustível | W32: =SUM(K32:V32) -> 0 | Z32: 642.5 | AD32: 0 | AE32: 0 | AF32: 0 | AG32: 0 | AH32: 0 | AI32: 0 | AJ32: =SUM(X32:AE32) -> 642.5 | AK32: =SUM(X32:AI32) -> 642.5 | AL32: 0 | AM32: 0 | AN32: 0 | AO32: 0 | AP32: 0 | AQ32: 0 | AR32: 0 | AS32: 0 | AT32: 0 | AU32: 0 | AV32: 0 | AW32: 0 | AX32: =IF(COUNT($AL32:$AW32)=0,"",SUM($AL32:$AW32)) -> 0 | AY32: =IF($AX32="","",$AX32-IF($W32="",0,$W32)) -> 0 | AZ32: =IF($AX32="","",$AX32-IF($AK32="",0,$AK32)) -> -642.5 | BB32: Rascunho
A33: =IF(OR($B33="",$D33="",$G33=""),"",ROW()-7) -> 26 | B33: ECEL COMERCIALIZADORA | C33: =IF($B33="","",IFERROR(INDEX(Apoio!$L$3:$L$81,MATCH($B33,Apoio!$K$3:$K$81,0)),"")) -> COMERCIALIZADORA | D33: C104 | E33: =IF($D33="","",IFERROR(INDEX(Apoio!$C$3:$C$81,MATCH($D33,Apoio!$B$3:$B$81,0)),"")) -> TI | F33: =IF($D33="","",IFERROR(INDEX(Apoio!$D$3:$D$81,MATCH($D33,Apoio!$B$3:$B$81,0)),"")) -> Marcelo Bronzatti | G33: =IF($H33="","",IFERROR(_xlfn.XLOOKUP(H33,'De x Para DRE'!C:C,'De x Para DRE'!B:B),"")) -> 5110100706 | H33: DESPESA LOCAÇÃO DE IMPRESSORAS | I33: =IF($G33="","",IFERROR(INDEX('De x Para DRE'!$E$3:$E$210,MATCH($G33,'De x Para DRE'!$B$3:$B$210,0)),"")) -> 3.1 G&A | J33: Locação Impressoras / RBS NASCIMENTO | N33: 600 | O33: 600 | P33: 600 | Q33: 600 | R33: 600 | S33: 600 | T33: 600 | U33: 600 | V33: 600 | W33: =SUM(K33:V33) -> 5400 | Z33: 600 | AB33: 600 | AC33: 600 | AD33: 600 | AE33: 600 | AF33: 600 | AG33: 600 | AH33: 600 | AI33: 600 | AJ33: =SUM(X33:AE33) -> 3000 | AK33: =SUM(X33:AI33) -> 5400 | AL33: 600 | AM33: 600 | AN33: 600 | AO33: 600 | AP33: 600 | AQ33: 600 | AR33: 600 | AS33: 600 | AT33: 600 | AU33: 600 | AV33: 600 | AW33: 600 | AX33: =IF(COUNT($AL33:$AW33)=0,"",SUM($AL33:$AW33)) -> 7200 | AY33: =IF($AX33="","",$AX33-IF($W33="",0,$W33)) -> 1800 | AZ33: =IF($AX33="","",$AX33-IF($AK33="",0,$AK33)) -> 1800 | BB33: Rascunho
A34: =IF(OR($B34="",$D34="",$G34=""),"",ROW()-7) -> 27 | B34: ECEL COMERCIALIZADORA | C34: =IF($B34="","",IFERROR(INDEX(Apoio!$L$3:$L$81,MATCH($B34,Apoio!$K$3:$K$81,0)),"")) -> COMERCIALIZADORA | D34: C104 | E34: =IF($D34="","",IFERROR(INDEX(Apoio!$C$3:$C$81,MATCH($D34,Apoio!$B$3:$B$81,0)),"")) -> TI | F34: =IF($D34="","",IFERROR(INDEX(Apoio!$D$3:$D$81,MATCH($D34,Apoio!$B$3:$B$81,0)),"")) -> Marcelo Bronzatti | G34: =IF($H34="","",IFERROR(_xlfn.XLOOKUP(H34,'De x Para DRE'!C:C,'De x Para DRE'!B:B),"")) -> 5110100204 | H34: DESPESA MANUTENÇÃO VEÍCULOS LEVES | I34: =IF($G34="","",IFERROR(INDEX('De x Para DRE'!$E$3:$E$210,MATCH($G34,'De x Para DRE'!$B$3:$B$210,0)),"")) -> 3.1 G&A | J34: Manutenção de Veículos | W34: =SUM(K34:V34) -> 0 | Z34: =647.5*3 -> 1942.5 | AD34: 0 | AE34: 0 | AF34: 0 | AG34: 0 | AH34: 0 | AI34: 0 | AJ34: =SUM(X34:AE34) -> 1942.5 | AK34: =SUM(X34:AI34) -> 1942.5 | AL34: 0 | AM34: 0 | AN34: 0 | AO34: 0 | AP34: 0 | AQ34: 0 | AR34: 0 | AS34: 0 | AT34: 0 | AU34: 0 | AV34: 0 | AW34: 0 | AX34: =IF(COUNT($AL34:$AW34)=0,"",SUM($AL34:$AW34)) -> 0 | AY34: =IF($AX34="","",$AX34-IF($W34="",0,$W34)) -> 0 | AZ34: =IF($AX34="","",$AX34-IF($AK34="",0,$AK34)) -> -1942.5 | BB34: Rascunho
A35: =IF(OR($B35="",$D35="",$G35=""),"",ROW()-7) -> 28 | B35: ECEL COMERCIALIZADORA | C35: =IF($B35="","",IFERROR(INDEX(Apoio!$L$3:$L$81,MATCH($B35,Apoio!$K$3:$K$81,0)),"")) -> COMERCIALIZADORA | D35: C104 | E35: =IF($D35="","",IFERROR(INDEX(Apoio!$C$3:$C$81,MATCH($D35,Apoio!$B$3:$B$81,0)),"")) -> TI | F35: =IF($D35="","",IFERROR(INDEX(Apoio!$D$3:$D$81,MATCH($D35,Apoio!$B$3:$B$81,0)),"")) -> Marcelo Bronzatti | G35: =IF($H35="","",IFERROR(_xlfn.XLOOKUP(H35,'De x Para DRE'!C:C,'De x Para DRE'!B:B),"")) -> 5110100802 | H35: DESPESA REFEIÇÕES E LANCHES | I35: =IF($G35="","",IFERROR(INDEX('De x Para DRE'!$E$3:$E$210,MATCH($G35,'De x Para DRE'!$B$3:$B$210,0)),"")) -> 3.1 G&A | J35: Refeições | K35: 181.1275 | L35: 181.1275 | M35: 181.1275 | N35: 181.1275 | O35: 181.1275 | P35: 181.1275 | Q35: 181.1275 | R35: 181.1275 | S35: 181.1275 | T35: 181.1275 | U35: 181.1275 | V35: 181.1275 | W35: =SUM(K35:V35) -> 2173.53 | X35: 0 | Y35: 0 | Z35: 1099.92 | AA35: 0 | AB35: 0 | AC35: 0 | AD35: 0 | AE35: 0 | AF35: 0 | AG35: 0 | AH35: 0 | AI35: 0 | AJ35: =SUM(X35:AE35) -> 1099.92 | AK35: =SUM(X35:AI35) -> 1099.92 | AL35: 200 | AM35: 200 | AN35: 200 | AO35: 200 | AP35: 200 | AQ35: 200 | AR35: 200 | AS35: 200 | AT35: 200 | AU35: 200 | AV35: 200 | AW35: 200 | AX35: =IF(COUNT($AL35:$AW35)=0,"",SUM($AL35:$AW35)) -> 2400 | AY35: =IF($AX35="","",$AX35-IF($W35="",0,$W35)) -> 226.47 | AZ35: =IF($AX35="","",$AX35-IF($AK35="",0,$AK35)) -> 1300.08 | BB35: Rascunho
A36: =IF(OR($B36="",$D36="",$G36=""),"",ROW()-7) -> 29 | B36: ECEL COMERCIALIZADORA | C36: =IF($B36="","",IFERROR(INDEX(Apoio!$L$3:$L$81,MATCH($B36,Apoio!$K$3:$K$81,0)),"")) -> COMERCIALIZADORA | D36: C104 | E36: =IF($D36="","",IFERROR(INDEX(Apoio!$C$3:$C$81,MATCH($D36,Apoio!$B$3:$B$81,0)),"")) -> TI | F36: =IF($D36="","",IFERROR(INDEX(Apoio!$D$3:$D$81,MATCH($D36,Apoio!$B$3:$B$81,0)),"")) -> Marcelo Bronzatti | G36: =IF($H36="","",IFERROR(_xlfn.XLOOKUP(H36,'De x Para DRE'!C:C,'De x Para DRE'!B:B),"")) -> 5110100801 | H36: DESPESA TÁXI E LOCOMOÇÕES FUNCIONÁRIOS | I36: =IF($G36="","",IFERROR(INDEX('De x Para DRE'!$E$3:$E$210,MATCH($G36,'De x Para DRE'!$B$3:$B$210,0)),"")) -> 3.1 G&A | J36: Locomoção | K36: 429.13125 | L36: 429.13125 | M36: 429.13125 | N36: 429.13125 | O36: 429.13125 | P36: 429.13125 | Q36: 429.13125 | R36: 429.13125 | S36: 429.13125 | T36: 429.13125 | U36: 429.13125 | V36: 429.13125 | W36: =SUM(K36:V36) -> 5149.575 | X36: 0 | Y36: =200+805.08 -> 1005.08 | Z36: 660.38 | AA36: 686.37 | AB36: 227.12 | AC36: 202.39 | AE36: 43.99 | AF36: 0 | AG36: 0 | AH36: 0 | AI36: 0 | AJ36: =SUM(X36:AE36) -> 2825.33 | AK36: =SUM(X36:AI36) -> 2825.33 | AL36: 0 | AM36: 0 | AN36: 0 | AO36: 0 | AP36: 0 | AQ36: 0 | AR36: 0 | AS36: 0 | AT36: 0 | AU36: 0 | AV36: 0 | AW36: 0 | AX36: =IF(COUNT($AL36:$AW36)=0,"",SUM($AL36:$AW36)) -> 0 | AY36: =IF($AX36="","",$AX36-IF($W36="",0,$W36)) -> -5149.575 | AZ36: =IF($AX36="","",$AX36-IF($AK36="",0,$AK36)) -> -2825.33 | BB36: Rascunho
A37: =IF(OR($B37="",$D37="",$G37=""),"",ROW()-7) -> 30 | B37: ECEL COMERCIALIZADORA | C37: =IF($B37="","",IFERROR(INDEX(Apoio!$L$3:$L$81,MATCH($B37,Apoio!$K$3:$K$81,0)),"")) -> COMERCIALIZADORA | D37: C104 | E37: =IF($D37="","",IFERROR(INDEX(Apoio!$C$3:$C$81,MATCH($D37,Apoio!$B$3:$B$81,0)),"")) -> TI | F37: =IF($D37="","",IFERROR(INDEX(Apoio!$D$3:$D$81,MATCH($D37,Apoio!$B$3:$B$81,0)),"")) -> Marcelo Bronzatti | G37: =IF($H37="","",IFERROR(_xlfn.XLOOKUP(H37,'De x Para DRE'!C:C,'De x Para DRE'!B:B),"")) -> 5110100707 | H37: DESPESA MANUTENÇÃO DE HARDWARE/SOFTWARE | I37: =IF($G37="","",IFERROR(INDEX('De x Para DRE'!$E$3:$E$210,MATCH($G37,'De x Para DRE'!$B$3:$B$210,0)),"")) -> 3.1 G&A | J37: Westcon - Licenças Meraki | K37: 31010.85 | W37: =SUM(K37:V37) -> 31010.85 | Y37: 21336.05 | Z37: 9674.79 | AD37: 0 | AE37: 0 | AF37: 0 | AG37: 0 | AH37: 0 | AI37: 0 | AJ37: =SUM(X37:AE37) -> 31010.84 | AK37: =SUM(X37:AI37) -> 31010.84 | AL37: 0 | AM37: 0 | AN37: 0 | AO37: 0 | AP37: 0 | AQ37: 0 | AR37: 0 | AS37: 0 | AT37: 0 | AU37: 0 | AV37: 0 | AW37: 0 | AX37: =IF(COUNT($AL37:$AW37)=0,"",SUM($AL37:$AW37)) -> 0 | AY37: =IF($AX37="","",$AX37-IF($W37="",0,$W37)) -> -31010.85 | AZ37: =IF($AX37="","",$AX37-IF($AK37="",0,$AK37)) -> -31010.84 | BB37: Rascunho
A38: =IF(OR($B38="",$D38="",$G38=""),"",ROW()-7) -> 31 | B38: ECEL COMERCIALIZADORA | C38: =IF($B38="","",IFERROR(INDEX(Apoio!$L$3:$L$81,MATCH($B38,Apoio!$K$3:$K$81,0)),"")) -> COMERCIALIZADORA | D38: C104 | E38: =IF($D38="","",IFERROR(INDEX(Apoio!$C$3:$C$81,MATCH($D38,Apoio!$B$3:$B$81,0)),"")) -> TI | F38: =IF($D38="","",IFERROR(INDEX(Apoio!$D$3:$D$81,MATCH($D38,Apoio!$B$3:$B$81,0)),"")) -> Marcelo Bronzatti | G38: =IF($H38="","",IFERROR(_xlfn.XLOOKUP(H38,'De x Para DRE'!C:C,'De x Para DRE'!B:B),"")) -> 5110100707 | H38: DESPESA MANUTENÇÃO DE HARDWARE/SOFTWARE | I38: =IF($G38="","",IFERROR(INDEX('De x Para DRE'!$E$3:$E$210,MATCH($G38,'De x Para DRE'!$B$3:$B$210,0)),"")) -> 3.1 G&A | J38: Cisco Umbrella - Anual | T38: 13000 | W38: =SUM(K38:V38) -> 13000 | AD38: 0 | AE38: 0 | AF38: 0 | AG38: 13000 | AH38: 0 | AI38: 0 | AJ38: =SUM(X38:AE38) -> 0 | AK38: =SUM(X38:AI38) -> 13000 | AL38: 0 | AM38: 0 | AN38: 0 | AO38: 0 | AP38: 0 | AQ38: 0 | AR38: 0 | AS38: 0 | AT38: 0 | AU38: 0 | AV38: 0 | AW38: 0 | AX38: =IF(COUNT($AL38:$AW38)=0,"",SUM($AL38:$AW38)) -> 0 | AY38: =IF($AX38="","",$AX38-IF($W38="",0,$W38)) -> -13000 | AZ38: =IF($AX38="","",$AX38-IF($AK38="",0,$AK38)) -> -13000 | BB38: Rascunho
A39: =IF(OR($B39="",$D39="",$G39=""),"",ROW()-7) -> 32 | B39: ECEL COMERCIALIZADORA | C39: =IF($B39="","",IFERROR(INDEX(Apoio!$L$3:$L$81,MATCH($B39,Apoio!$K$3:$K$81,0)),"")) -> COMERCIALIZADORA | D39: C104 | E39: =IF($D39="","",IFERROR(INDEX(Apoio!$C$3:$C$81,MATCH($D39,Apoio!$B$3:$B$81,0)),"")) -> TI | F39: =IF($D39="","",IFERROR(INDEX(Apoio!$D$3:$D$81,MATCH($D39,Apoio!$B$3:$B$81,0)),"")) -> Marcelo Bronzatti | G39: =IF($H39="","",IFERROR(_xlfn.XLOOKUP(H39,'De x Para DRE'!C:C,'De x Para DRE'!B:B),"")) -> 5110100702 | H39: SISTEMAS DE GESTÃO ADM/OPERACIONAL | I39: =IF($G39="","",IFERROR(INDEX('De x Para DRE'!$E$3:$E$210,MATCH($G39,'De x Para DRE'!$B$3:$B$210,0)),"")) -> 3.1 G&A | J39: Heroku | K39: 1500 | L39: 1500 | M39: 1500 | N39: 1500 | O39: 1500 | P39: 1500 | Q39: 1500 | R39: 1500 | S39: 1500 | T39: 1500 | U39: 1500 | V39: 1500 | W39: =SUM(K39:V39) -> 18000 | X39: 1250.92 | Y39: 1368.57 | Z39: 1332.5 | AA39: 1332.56 | AB39: 1308.55 | AC39: 1247.21 | AD39: 1247.21 | AE39: 1247.21 | AF39: 1500 | AG39: 1500 | AH39: 1500 | AI39: 1500 | AJ39: =SUM(X39:AE39) -> 10334.73 | AK39: =SUM(X39:AI39) -> 16334.73 | AL39: 2000 | AM39: 2000 | AN39: 2000 | AO39: 2000 | AP39: 2000 | AQ39: 2000 | AR39: 2000 | AS39: 2000 | AT39: 2000 | AU39: 2000 | AV39: 2000 | AW39: 2000 | AX39: =IF(COUNT($AL39:$AW39)=0,"",SUM($AL39:$AW39)) -> 24000 | AY39: =IF($AX39="","",$AX39-IF($W39="",0,$W39)) -> 6000 | AZ39: =IF($AX39="","",$AX39-IF($AK39="",0,$AK39)) -> 7665.27 | BA39: Hosp.Boletador e Integra | BB39: Rascunho
A40: =IF(OR($B40="",$D40="",$G40=""),"",ROW()-7) -> 33 | B40: ECEL COMERCIALIZADORA | C40: =IF($B40="","",IFERROR(INDEX(Apoio!$L$3:$L$81,MATCH($B40,Apoio!$K$3:$K$81,0)),"")) -> COMERCIALIZADORA | D40: C104 | E40: =IF($D40="","",IFERROR(INDEX(Apoio!$C$3:$C$81,MATCH($D40,Apoio!$B$3:$B$81,0)),"")) -> TI | F40: =IF($D40="","",IFERROR(INDEX(Apoio!$D$3:$D$81,MATCH($D40,Apoio!$B$3:$B$81,0)),"")) -> Marcelo Bronzatti | G40: =IF($H40="","",IFERROR(_xlfn.XLOOKUP(H40,'De x Para DRE'!C:C,'De x Para DRE'!B:B),"")) -> 5110100702 | H40: SISTEMAS DE GESTÃO ADM/OPERACIONAL | I40: =IF($G40="","",IFERROR(INDEX('De x Para DRE'!$E$3:$E$210,MATCH($G40,'De x Para DRE'!$B$3:$B$210,0)),"")) -> 3.1 G&A | J40: Github - Repositório de Códigos Fontes | K40: 750 | L40: 750 | M40: 750 | N40: 750 | O40: 750 | P40: 750 | Q40: 750 | R40: 750 | S40: 750 | T40: 750 | U40: 750 | V40: 750 | W40: =SUM(K40:V40) -> 9000 | X40: 657.3 | Y40: 672.89 | Z40: 693.75 | AA40: 840.7 | AB40: 717.61 | AC40: 593.34 | AD40: 750 | AE40: 750 | AF40: 750 | AG40: 750 | AH40: 750 | AI40: 750 | AJ40: =SUM(X40:AE40) -> 5675.59 | AK40: =SUM(X40:AI40) -> 8675.59 | AL40: 1000 | AM40: 1000 | AN40: 1000 | AO40: 1000 | AP40: 1000 | AQ40: 1000 | AR40: 1000 | AS40: 1000 | AT40: 1000 | AU40: 1000 | AV40: 1000 | AW40: 1000 | AX40: =IF(COUNT($AL40:$AW40)=0,"",SUM($AL40:$AW40)) -> 12000 | AY40: =IF($AX40="","",$AX40-IF($W40="",0,$W40)) -> 3000 | AZ40: =IF($AX40="","",$AX40-IF($AK40="",0,$AK40)) -> 3324.41 | BB40: Rascunho
A41: =IF(OR($B41="",$D41="",$G41=""),"",ROW()-7) -> 34 | B41: ECEL COMERCIALIZADORA | C41: =IF($B41="","",IFERROR(INDEX(Apoio!$L$3:$L$81,MATCH($B41,Apoio!$K$3:$K$81,0)),"")) -> COMERCIALIZADORA | D41: C104 | E41: =IF($D41="","",IFERROR(INDEX(Apoio!$C$3:$C$81,MATCH($D41,Apoio!$B$3:$B$81,0)),"")) -> TI | F41: =IF($D41="","",IFERROR(INDEX(Apoio!$D$3:$D$81,MATCH($D41,Apoio!$B$3:$B$81,0)),"")) -> Marcelo Bronzatti | G41: =IF($H41="","",IFERROR(_xlfn.XLOOKUP(H41,'De x Para DRE'!C:C,'De x Para DRE'!B:B),"")) -> 5110100702 | H41: SISTEMAS DE GESTÃO ADM/OPERACIONAL | I41: =IF($G41="","",IFERROR(INDEX('De x Para DRE'!$E$3:$E$210,MATCH($G41,'De x Para DRE'!$B$3:$B$210,0)),"")) -> 3.1 G&A | J41: Adobe Creative Cloud | K41: 747 | L41: 747 | M41: 747 | N41: 747 | O41: 747 | P41: 800 | Q41: 800 | R41: 800 | S41: 800 | T41: 800 | U41: 800 | V41: 800 | W41: =SUM(K41:V41) -> 9335 | X41: 747 | Y41: 747 | Z41: 747 | AA41: 380 | AB41: 747 | AC41: 747 | AD41: 747 | AE41: 747 | AF41: 800 | AG41: 800 | AH41: 800 | AI41: 800 | AJ41: =SUM(X41:AE41) -> 5609 | AK41: =SUM(X41:AI41) -> 8809 | AL41: =430*2 -> 860 | AM41: =430*2 -> 860 | AN41: =430*2 -> 860 | AO41: =430*2 -> 860 | AP41: =430*2 -> 860 | AQ41: =430*2 -> 860 | AR41: =430*2 -> 860 | AS41: =430*2 -> 860 | ... AW41: =430*2 -> 860 | AX41: =IF(COUNT($AL41:$AW41)=0,"",SUM($AL41:$AW41)) -> 10320 | AY41: =IF($AX41="","",$AX41-IF($W41="",0,$W41)) -> 985 | AZ41: =IF($AX41="","",$AX41-IF($AK41="",0,$AK41)) -> 1511 | BB41: Rascunho
A42: =IF(OR($B42="",$D42="",$G42=""),"",ROW()-7) -> 35 | B42: ECEL COMERCIALIZADORA | C42: =IF($B42="","",IFERROR(INDEX(Apoio!$L$3:$L$81,MATCH($B42,Apoio!$K$3:$K$81,0)),"")) -> COMERCIALIZADORA | D42: C104 | E42: =IF($D42="","",IFERROR(INDEX(Apoio!$C$3:$C$81,MATCH($D42,Apoio!$B$3:$B$81,0)),"")) -> TI | F42: =IF($D42="","",IFERROR(INDEX(Apoio!$D$3:$D$81,MATCH($D42,Apoio!$B$3:$B$81,0)),"")) -> Marcelo Bronzatti | G42: =IF($H42="","",IFERROR(_xlfn.XLOOKUP(H42,'De x Para DRE'!C:C,'De x Para DRE'!B:B),"")) -> 5110100702 | H42: SISTEMAS DE GESTÃO ADM/OPERACIONAL | I42: =IF($G42="","",IFERROR(INDEX('De x Para DRE'!$E$3:$E$210,MATCH($G42,'De x Para DRE'!$B$3:$B$210,0)),"")) -> 3.1 G&A | J42: Claude AI | K42: 105.63 | L42: 105.63 | M42: 105.63 | N42: 105.63 | O42: 105.63 | P42: 105.63 | Q42: 105.63 | R42: 105.63 | S42: 105.63 | T42: 105.63 | U42: 105.63 | V42: 105.63 | W42: =SUM(K42:V42) -> 1267.56 | AA42: 118.62 | AB42: 116.85 | AC42: 116.15 | AD42: 105.63 | AE42: 105.63 | AF42: 105.63 | AG42: 105.63 | AH42: 105.63 | AI42: 105.63 | AJ42: =SUM(X42:AE42) -> 562.88 | AK42: =SUM(X42:AI42) -> 985.4 | AL42: 1000 | AM42: 1000 | AN42: 1000 | AO42: 1000 | AP42: 1000 | AQ42: 1000 | AR42: 1000 | AS42: 1000 | AT42: 1000 | AU42: 1000 | AV42: 1000 | AW42: 1000 | AX42: =IF(COUNT($AL42:$AW42)=0,"",SUM($AL42:$AW42)) -> 12000 | AY42: =IF($AX42="","",$AX42-IF($W42="",0,$W42)) -> 10732.44 | AZ42: =IF($AX42="","",$AX42-IF($AK42="",0,$AK42)) -> 11014.6 | BB42: Rascunho
A43: =IF(OR($B43="",$D43="",$G43=""),"",ROW()-7) -> 36 | B43: ECEL COMERCIALIZADORA | C43: =IF($B43="","",IFERROR(INDEX(Apoio!$L$3:$L$81,MATCH($B43,Apoio!$K$3:$K$81,0)),"")) -> COMERCIALIZADORA | D43: C104 | E43: =IF($D43="","",IFERROR(INDEX(Apoio!$C$3:$C$81,MATCH($D43,Apoio!$B$3:$B$81,0)),"")) -> TI | F43: =IF($D43="","",IFERROR(INDEX(Apoio!$D$3:$D$81,MATCH($D43,Apoio!$B$3:$B$81,0)),"")) -> Marcelo Bronzatti | G43: =IF($H43="","",IFERROR(_xlfn.XLOOKUP(H43,'De x Para DRE'!C:C,'De x Para DRE'!B:B),"")) -> 5110100707 | H43: DESPESA MANUTENÇÃO DE HARDWARE/SOFTWARE | I43: =IF($G43="","",IFERROR(INDEX('De x Para DRE'!$E$3:$E$210,MATCH($G43,'De x Para DRE'!$B$3:$B$210,0)),"")) -> 3.1 G&A | J43: Iperius Backup - Anual | L43: 1500 | W43: =SUM(K43:V43) -> 1500 | AD43: 0 | AE43: 0 | AF43: 0 | AG43: 0 | AH43: 0 | AI43: 0 | AJ43: =SUM(X43:AE43) -> 0 | AK43: =SUM(X43:AI43) -> 0 | AL43: 0 | AM43: 0 | AN43: 0 | AO43: 0 | AP43: 0 | AQ43: 0 | AR43: 0 | AS43: 0 | AT43: 0 | AU43: 0 | AV43: 0 | AW43: 0 | AX43: =IF(COUNT($AL43:$AW43)=0,"",SUM($AL43:$AW43)) -> 0 | AY43: =IF($AX43="","",$AX43-IF($W43="",0,$W43)) -> -1500 | AZ43: =IF($AX43="","",$AX43-IF($AK43="",0,$AK43)) -> 0 | BB43: Rascunho
A44: =IF(OR($B44="",$D44="",$G44=""),"",ROW()-7) -> 37 | B44: ECEL COMERCIALIZADORA | C44: =IF($B44="","",IFERROR(INDEX(Apoio!$L$3:$L$81,MATCH($B44,Apoio!$K$3:$K$81,0)),"")) -> COMERCIALIZADORA | D44: C104 | E44: =IF($D44="","",IFERROR(INDEX(Apoio!$C$3:$C$81,MATCH($D44,Apoio!$B$3:$B$81,0)),"")) -> TI | F44: =IF($D44="","",IFERROR(INDEX(Apoio!$D$3:$D$81,MATCH($D44,Apoio!$B$3:$B$81,0)),"")) -> Marcelo Bronzatti | G44: =IF($H44="","",IFERROR(_xlfn.XLOOKUP(H44,'De x Para DRE'!C:C,'De x Para DRE'!B:B),"")) -> 5110100201 | H44: MANUTENÇÃO DE MÁQ. EQUIP. E INSTALAÇÕES-PJ | I44: =IF($G44="","",IFERROR(INDEX('De x Para DRE'!$E$3:$E$210,MATCH($G44,'De x Para DRE'!$B$3:$B$210,0)),"")) -> 3.1 G&A | J44: Manutenção de Ativos | K44: 333.33333 | L44: 333.33333 | M44: 333.33333 | N44: 333.33333 | O44: 333.33333 | P44: 333.33333 | Q44: 333.33333 | R44: 333.33333 | S44: 333.33333 | T44: 333.33333 | U44: 333.33333 | V44: 333.33333 | W44: =SUM(K44:V44) -> 4000 | X44: 500 | Y44: =1059.6+400+819.5 -> 2279.1 | Z44: 957.2 | AC44: 233.92 | AD44: 0 | AE44: 233.92 | AF44: 333.33333 | AG44: 333.33333 | AH44: 333.33333 | AI44: 333.33333 | AJ44: =SUM(X44:AE44) -> 4204.14 | AK44: =SUM(X44:AI44) -> 5537.4733 | AL44: 800 | AM44: 800 | AN44: 800 | AO44: 800 | AP44: 800 | AQ44: 800 | AR44: 800 | AS44: 800 | AT44: 800 | AU44: 800 | AV44: 800 | AW44: 800 | AX44: =IF(COUNT($AL44:$AW44)=0,"",SUM($AL44:$AW44)) -> 9600 | AY44: =IF($AX44="","",$AX44-IF($W44="",0,$W44)) -> 5600 | AZ44: =IF($AX44="","",$AX44-IF($AK44="",0,$AK44)) -> 4062.5267 | BB44: Rascunho
A45: =IF(OR($B45="",$D45="",$G45=""),"",ROW()-7) -> 38 | B45: ECEL COMERCIALIZADORA | C45: =IF($B45="","",IFERROR(INDEX(Apoio!$L$3:$L$81,MATCH($B45,Apoio!$K$3:$K$81,0)),"")) -> COMERCIALIZADORA | D45: C104 | E45: =IF($D45="","",IFERROR(INDEX(Apoio!$C$3:$C$81,MATCH($D45,Apoio!$B$3:$B$81,0)),"")) -> TI | F45: =IF($D45="","",IFERROR(INDEX(Apoio!$D$3:$D$81,MATCH($D45,Apoio!$B$3:$B$81,0)),"")) -> Marcelo Bronzatti | G45: =IF($H45="","",IFERROR(_xlfn.XLOOKUP(H45,'De x Para DRE'!C:C,'De x Para DRE'!B:B),"")) -> 5110100702 | H45: SISTEMAS DE GESTÃO ADM/OPERACIONAL | I45: =IF($G45="","",IFERROR(INDEX('De x Para DRE'!$E$3:$E$210,MATCH($G45,'De x Para DRE'!$B$3:$B$210,0)),"")) -> 3.1 G&A | J45: Godaddy - Registro de Domínio Anual | L45: 700 | W45: =SUM(K45:V45) -> 700 | AD45: 0 | AE45: 0 | AF45: 0 | AG45: 0 | AH45: 0 | AI45: 0 | AJ45: =SUM(X45:AE45) -> 0 | AK45: =SUM(X45:AI45) -> 0 | AL45: 0 | AM45: 0 | AN45: 0 | AO45: 0 | AP45: 0 | AQ45: 0 | AR45: 0 | AS45: 0 | AT45: 0 | AU45: 0 | AV45: 0 | AW45: 0 | AX45: =IF(COUNT($AL45:$AW45)=0,"",SUM($AL45:$AW45)) -> 0 | AY45: =IF($AX45="","",$AX45-IF($W45="",0,$W45)) -> -700 | AZ45: =IF($AX45="","",$AX45-IF($AK45="",0,$AK45)) -> 0 | BB45: Rascunho
A46: =IF(OR($B46="",$D46="",$G46=""),"",ROW()-7) -> 39 | B46: ECEL COMERCIALIZADORA | C46: =IF($B46="","",IFERROR(INDEX(Apoio!$L$3:$L$81,MATCH($B46,Apoio!$K$3:$K$81,0)),"")) -> COMERCIALIZADORA | D46: C202 | E46: =IF($D46="","",IFERROR(INDEX(Apoio!$C$3:$C$81,MATCH($D46,Apoio!$B$3:$B$81,0)),"")) -> Middle Office | F46: =IF($D46="","",IFERROR(INDEX(Apoio!$D$3:$D$81,MATCH($D46,Apoio!$B$3:$B$81,0)),"")) -> Rafael Lemos | G46: =IF($H46="","",IFERROR(_xlfn.XLOOKUP(H46,'De x Para DRE'!C:C,'De x Para DRE'!B:B),"")) -> 5110100501 | H46: DESPESA ASSESSORIA -PJ | I46: =IF($G46="","",IFERROR(INDEX('De x Para DRE'!$E$3:$E$210,MATCH($G46,'De x Para DRE'!$B$3:$B$210,0)),"")) -> 3.1 G&A | J46: Serviço de Meteorologia - CONMET / FMG Energy Price | K46: 5500 | L46: 5500 | M46: 5500 | N46: 5500 | O46: 5500 | P46: 5500 | Q46: 5500 | R46: 5500 | S46: 5500 | T46: 5500 | U46: 5500 | V46: 5500 | W46: =SUM(K46:V46) -> 66000 | X46: 5000 | Y46: 5000 | Z46: 5000 | AA46: =5000+4500 -> 9500 | AB46: =5000+4500 -> 9500 | AC46: =4500*2 -> 9000 | AD46: 4500 | AE46: 4500 | AF46: 4500 | AG46: 4500 | AH46: 4500 | AI46: 4500 | AJ46: =SUM(X46:AE46) -> 52000 | AK46: =SUM(X46:AI46) -> 70000 | AL46: 0 | AM46: 0 | AN46: 0 | AO46: 0 | AP46: 0 | AQ46: 0 | AR46: 0 | AS46: 0 | AT46: 0 | AU46: 0 | AV46: 0 | AW46: 0 | AX46: =IF(COUNT($AL46:$AW46)=0,"",SUM($AL46:$AW46)) -> 0 | AY46: =IF($AX46="","",$AX46-IF($W46="",0,$W46)) -> -66000 | AZ46: =IF($AX46="","",$AX46-IF($AK46="",0,$AK46)) -> -70000 | BB46: Rascunho
A47: =IF(OR($B47="",$D47="",$G47=""),"",ROW()-7) -> 40 | B47: ECEL COMERCIALIZADORA | C47: =IF($B47="","",IFERROR(INDEX(Apoio!$L$3:$L$81,MATCH($B47,Apoio!$K$3:$K$81,0)),"")) -> COMERCIALIZADORA | D47: C202 | E47: =IF($D47="","",IFERROR(INDEX(Apoio!$C$3:$C$81,MATCH($D47,Apoio!$B$3:$B$81,0)),"")) -> Middle Office | F47: =IF($D47="","",IFERROR(INDEX(Apoio!$D$3:$D$81,MATCH($D47,Apoio!$B$3:$B$81,0)),"")) -> Rafael Lemos | G47: =IF($H47="","",IFERROR(_xlfn.XLOOKUP(H47,'De x Para DRE'!C:C,'De x Para DRE'!B:B),"")) -> 5110100501 | H47: DESPESA ASSESSORIA -PJ | I47: =IF($G47="","",IFERROR(INDEX('De x Para DRE'!$E$3:$E$210,MATCH($G47,'De x Para DRE'!$B$3:$B$210,0)),"")) -> 3.1 G&A | J47: Serviço de Meteorologia - TEMPO OK | W47: =SUM(K47:V47) -> 0 | X47: 7834.63 | Z47: 7834.63 | AD47: 0 | AE47: 0 | AF47: 0 | AG47: 0 | AH47: 0 | AI47: 0 | AJ47: =SUM(X47:AE47) -> 15669.26 | AK47: =SUM(X47:AI47) -> 15669.26 | AL47: 0 | AM47: 0 | AN47: 0 | AO47: 0 | AP47: 0 | AQ47: 0 | AR47: 0 | AS47: 0 | AT47: 0 | AU47: 0 | AV47: 0 | AW47: 0 | AX47: =IF(COUNT($AL47:$AW47)=0,"",SUM($AL47:$AW47)) -> 0 | AY47: =IF($AX47="","",$AX47-IF($W47="",0,$W47)) -> 0 | AZ47: =IF($AX47="","",$AX47-IF($AK47="",0,$AK47)) -> -15669.26 | BB47: Rascunho
A48: =IF(OR($B48="",$D48="",$G48=""),"",ROW()-7) -> 41 | B48: ECEL COMERCIALIZADORA | C48: =IF($B48="","",IFERROR(INDEX(Apoio!$L$3:$L$81,MATCH($B48,Apoio!$K$3:$K$81,0)),"")) -> COMERCIALIZADORA | D48: C202 | E48: =IF($D48="","",IFERROR(INDEX(Apoio!$C$3:$C$81,MATCH($D48,Apoio!$B$3:$B$81,0)),"")) -> Middle Office | F48: =IF($D48="","",IFERROR(INDEX(Apoio!$D$3:$D$81,MATCH($D48,Apoio!$B$3:$B$81,0)),"")) -> Rafael Lemos | G48: =IF($H48="","",IFERROR(_xlfn.XLOOKUP(H48,'De x Para DRE'!C:C,'De x Para DRE'!B:B),"")) -> 5110100903 | H48: DESPESA COM ASSINATURAS DE JORNAIS E REVISTAS | I48: =IF($G48="","",IFERROR(INDEX('De x Para DRE'!$E$3:$E$210,MATCH($G48,'De x Para DRE'!$B$3:$B$210,0)),"")) -> 3.1 G&A | J48: Assinatura de Meteorologia - WeatherBell | K48: 200 | L48: 200 | M48: 200 | N48: 200 | O48: 200 | P48: 200 | Q48: 200 | R48: 200 | S48: 200 | T48: 200 | U48: 200 | V48: 200 | W48: =SUM(K48:V48) -> 2400 | AD48: 0 | AE48: 0 | AF48: 0 | AG48: 0 | AH48: 0 | AI48: 0 | AJ48: =SUM(X48:AE48) -> 0 | AK48: =SUM(X48:AI48) -> 0 | AL48: 0 | AM48: 0 | AN48: 0 | AO48: 0 | AP48: 0 | AQ48: 0 | AR48: 0 | AS48: 0 | AT48: 0 | AU48: 0 | AV48: 0 | AW48: 0 | AX48: =IF(COUNT($AL48:$AW48)=0,"",SUM($AL48:$AW48)) -> 0 | AY48: =IF($AX48="","",$AX48-IF($W48="",0,$W48)) -> -2400 | AZ48: =IF($AX48="","",$AX48-IF($AK48="",0,$AK48)) -> 0 | BB48: Rascunho
A49: =IF(OR($B49="",$D49="",$G49=""),"",ROW()-7) -> 42 | B49: ECEL COMERCIALIZADORA | C49: =IF($B49="","",IFERROR(INDEX(Apoio!$L$3:$L$81,MATCH($B49,Apoio!$K$3:$K$81,0)),"")) -> COMERCIALIZADORA | D49: C202 | E49: =IF($D49="","",IFERROR(INDEX(Apoio!$C$3:$C$81,MATCH($D49,Apoio!$B$3:$B$81,0)),"")) -> Middle Office | F49: =IF($D49="","",IFERROR(INDEX(Apoio!$D$3:$D$81,MATCH($D49,Apoio!$B$3:$B$81,0)),"")) -> Rafael Lemos | G49: =IF($H49="","",IFERROR(_xlfn.XLOOKUP(H49,'De x Para DRE'!C:C,'De x Para DRE'!B:B),"")) -> 5110100803 | H49: DESPESA COM HOSPEDAGEM | I49: =IF($G49="","",IFERROR(INDEX('De x Para DRE'!$E$3:$E$210,MATCH($G49,'De x Para DRE'!$B$3:$B$210,0)),"")) -> 3.1 G&A | J49: Hospedagens | K49: 58.975 | L49: 58.975 | M49: 58.975 | N49: 58.975 | O49: 58.975 | P49: 58.975 | Q49: 58.975 | R49: 58.975 | S49: 58.975 | T49: 58.975 | U49: 58.975 | V49: 58.975 | W49: =SUM(K49:V49) -> 707.7 | Z49: 727.2 | AD49: 0 | AE49: 0 | AF49: 0 | AG49: 0 | AH49: 0 | AI49: 0 | AJ49: =SUM(X49:AE49) -> 727.2 | AK49: =SUM(X49:AI49) -> 727.2 | AL49: 0 | AM49: 0 | AN49: 0 | AO49: 0 | AP49: 0 | AQ49: 0 | AR49: 0 | AS49: 0 | AT49: 0 | AU49: 0 | AV49: 0 | AW49: 0 | AX49: =IF(COUNT($AL49:$AW49)=0,"",SUM($AL49:$AW49)) -> 0 | AY49: =IF($AX49="","",$AX49-IF($W49="",0,$W49)) -> -707.7 | AZ49: =IF($AX49="","",$AX49-IF($AK49="",0,$AK49)) -> -727.2 | BB49: Rascunho
A50: =IF(OR($B50="",$D50="",$G50=""),"",ROW()-7) -> 43 | B50: ECEL COMERCIALIZADORA | C50: =IF($B50="","",IFERROR(INDEX(Apoio!$L$3:$L$81,MATCH($B50,Apoio!$K$3:$K$81,0)),"")) -> COMERCIALIZADORA | D50: C202 | E50: =IF($D50="","",IFERROR(INDEX(Apoio!$C$3:$C$81,MATCH($D50,Apoio!$B$3:$B$81,0)),"")) -> Middle Office | F50: =IF($D50="","",IFERROR(INDEX(Apoio!$D$3:$D$81,MATCH($D50,Apoio!$B$3:$B$81,0)),"")) -> Rafael Lemos | G50: =IF($H50="","",IFERROR(_xlfn.XLOOKUP(H50,'De x Para DRE'!C:C,'De x Para DRE'!B:B),"")) -> 5110100804 | H50: DESPESA COM PASSAGENS | I50: =IF($G50="","",IFERROR(INDEX('De x Para DRE'!$E$3:$E$210,MATCH($G50,'De x Para DRE'!$B$3:$B$210,0)),"")) -> 3.1 G&A | J50: Passagens | K50: 666.66667 | L50: 666.66667 | M50: 666.66667 | N50: 666.66667 | O50: 666.66667 | P50: 666.66667 | Q50: 666.66667 | R50: 666.66667 | S50: 666.66667 | T50: 666.66667 | U50: 666.66667 | V50: 666.66667 | W50: =SUM(K50:V50) -> 8000 | X50: 4837.99 | AD50: 0 | AE50: 0 | AF50: 0 | AG50: 0 | AH50: 0 | AI50: 0 | AJ50: =SUM(X50:AE50) -> 4837.99 | AK50: =SUM(X50:AI50) -> 4837.99 | AL50: 0 | AM50: 0 | AN50: 0 | AO50: 0 | AP50: 0 | AQ50: 0 | AR50: 0 | AS50: 0 | AT50: 0 | AU50: 0 | AV50: 0 | AW50: 0 | AX50: =IF(COUNT($AL50:$AW50)=0,"",SUM($AL50:$AW50)) -> 0 | AY50: =IF($AX50="","",$AX50-IF($W50="",0,$W50)) -> -8000 | AZ50: =IF($AX50="","",$AX50-IF($AK50="",0,$AK50)) -> -4837.99 | BB50: Rascunho
A51: =IF(OR($B51="",$D51="",$G51=""),"",ROW()-7) -> 44 | B51: ECEL COMERCIALIZADORA | C51: =IF($B51="","",IFERROR(INDEX(Apoio!$L$3:$L$81,MATCH($B51,Apoio!$K$3:$K$81,0)),"")) -> COMERCIALIZADORA | D51: C202 | E51: =IF($D51="","",IFERROR(INDEX(Apoio!$C$3:$C$81,MATCH($D51,Apoio!$B$3:$B$81,0)),"")) -> Middle Office | F51: =IF($D51="","",IFERROR(INDEX(Apoio!$D$3:$D$81,MATCH($D51,Apoio!$B$3:$B$81,0)),"")) -> Rafael Lemos | G51: =IF($H51="","",IFERROR(_xlfn.XLOOKUP(H51,'De x Para DRE'!C:C,'De x Para DRE'!B:B),"")) -> 5110100807 | H51: DESPESA LOCAÇÃO VEÍCULOS | I51: =IF($G51="","",IFERROR(INDEX('De x Para DRE'!$E$3:$E$210,MATCH($G51,'De x Para DRE'!$B$3:$B$210,0)),"")) -> 3.1 G&A | J51: Locação de Veículos | K51: 0 | L51: 0 | M51: 0 | N51: 0 | O51: 0 | P51: 0 | Q51: 0 | R51: 0 | S51: 0 | T51: 0 | U51: 0 | V51: 0 | W51: =SUM(K51:V51) -> 0 | AD51: 0 | AE51: 0 | AF51: 0 | AG51: 0 | AH51: 0 | AI51: 0 | AJ51: =SUM(X51:AE51) -> 0 | AK51: =SUM(X51:AI51) -> 0 | AL51: 0 | AM51: 0 | AN51: 0 | AO51: 0 | AP51: 0 | AQ51: 0 | AR51: 0 | AS51: 0 | AT51: 0 | AU51: 0 | AV51: 0 | AW51: 0 | AX51: =IF(COUNT($AL51:$AW51)=0,"",SUM($AL51:$AW51)) -> 0 | AY51: =IF($AX51="","",$AX51-IF($W51="",0,$W51)) -> 0 | AZ51: =IF($AX51="","",$AX51-IF($AK51="",0,$AK51)) -> 0 | BB51: Rascunho
A52: =IF(OR($B52="",$D52="",$G52=""),"",ROW()-7) -> 45 | B52: ECEL COMERCIALIZADORA | C52: =IF($B52="","",IFERROR(INDEX(Apoio!$L$3:$L$81,MATCH($B52,Apoio!$K$3:$K$81,0)),"")) -> COMERCIALIZADORA | D52: C202 | E52: =IF($D52="","",IFERROR(INDEX(Apoio!$C$3:$C$81,MATCH($D52,Apoio!$B$3:$B$81,0)),"")) -> Middle Office | F52: =IF($D52="","",IFERROR(INDEX(Apoio!$D$3:$D$81,MATCH($D52,Apoio!$B$3:$B$81,0)),"")) -> Rafael Lemos | G52: =IF($H52="","",IFERROR(_xlfn.XLOOKUP(H52,'De x Para DRE'!C:C,'De x Para DRE'!B:B),"")) -> 5110100406 | H52: SERVIÇOS TÉCNICOS | I52: =IF($G52="","",IFERROR(INDEX('De x Para DRE'!$E$3:$E$210,MATCH($G52,'De x Para DRE'!$B$3:$B$210,0)),"")) -> 3.1 G&A | J52: Hospedagens Nuvem - Google Suite | K52: 100 | L52: 100 | M52: 100 | N52: 100 | O52: 100 | P52: 100 | Q52: 100 | R52: 100 | S52: 100 | T52: 100 | U52: 100 | V52: 100 | W52: =SUM(K52:V52) -> 1200 | X52: 98 | Y52: 98 | AC52: 98 | AD52: 98 | AE52: 98 | AF52: 98 | AG52: 98 | AH52: 98 | AI52: 98 | AJ52: =SUM(X52:AE52) -> 490 | AK52: =SUM(X52:AI52) -> 882 | AL52: 0 | AM52: 0 | AN52: 0 | AO52: 0 | AP52: 0 | AQ52: 0 | AR52: 0 | AS52: 0 | AT52: 0 | AU52: 0 | AV52: 0 | AW52: 0 | AX52: =IF(COUNT($AL52:$AW52)=0,"",SUM($AL52:$AW52)) -> 0 | AY52: =IF($AX52="","",$AX52-IF($W52="",0,$W52)) -> -1200 | AZ52: =IF($AX52="","",$AX52-IF($AK52="",0,$AK52)) -> -882 | BB52: Rascunho
A53: =IF(OR($B53="",$D53="",$G53=""),"",ROW()-7) -> 46 | B53: ECEL COMERCIALIZADORA | C53: =IF($B53="","",IFERROR(INDEX(Apoio!$L$3:$L$81,MATCH($B53,Apoio!$K$3:$K$81,0)),"")) -> COMERCIALIZADORA | D53: C202 | E53: =IF($D53="","",IFERROR(INDEX(Apoio!$C$3:$C$81,MATCH($D53,Apoio!$B$3:$B$81,0)),"")) -> Middle Office | F53: =IF($D53="","",IFERROR(INDEX(Apoio!$D$3:$D$81,MATCH($D53,Apoio!$B$3:$B$81,0)),"")) -> Rafael Lemos | G53: =IF($H53="","",IFERROR(_xlfn.XLOOKUP(H53,'De x Para DRE'!C:C,'De x Para DRE'!B:B),"")) -> 5110100802 | H53: DESPESA REFEIÇÕES E LANCHES | I53: =IF($G53="","",IFERROR(INDEX('De x Para DRE'!$E$3:$E$210,MATCH($G53,'De x Para DRE'!$B$3:$B$210,0)),"")) -> 3.1 G&A | J53: Refeições | K53: 0 | L53: 0 | M53: 0 | N53: 0 | O53: 0 | P53: 0 | Q53: 0 | R53: 0 | S53: 0 | T53: 0 | U53: 0 | V53: 0 | W53: =SUM(K53:V53) -> 0 | AD53: 0 | AE53: 0 | AF53: 0 | AG53: 0 | AH53: 0 | AI53: 0 | AJ53: =SUM(X53:AE53) -> 0 | AK53: =SUM(X53:AI53) -> 0 | AL53: 0 | AM53: 0 | AN53: 0 | AO53: 0 | AP53: 0 | AQ53: 0 | AR53: 0 | AS53: 0 | AT53: 0 | AU53: 0 | AV53: 0 | AW53: 0 | AX53: =IF(COUNT($AL53:$AW53)=0,"",SUM($AL53:$AW53)) -> 0 | AY53: =IF($AX53="","",$AX53-IF($W53="",0,$W53)) -> 0 | AZ53: =IF($AX53="","",$AX53-IF($AK53="",0,$AK53)) -> 0 | BB53: Rascunho
A54: =IF(OR($B54="",$D54="",$G54=""),"",ROW()-7) -> 47 | B54: ECEL COMERCIALIZADORA | C54: =IF($B54="","",IFERROR(INDEX(Apoio!$L$3:$L$81,MATCH($B54,Apoio!$K$3:$K$81,0)),"")) -> COMERCIALIZADORA | D54: C202 | E54: =IF($D54="","",IFERROR(INDEX(Apoio!$C$3:$C$81,MATCH($D54,Apoio!$B$3:$B$81,0)),"")) -> Middle Office | F54: =IF($D54="","",IFERROR(INDEX(Apoio!$D$3:$D$81,MATCH($D54,Apoio!$B$3:$B$81,0)),"")) -> Rafael Lemos | G54: =IF($H54="","",IFERROR(_xlfn.XLOOKUP(H54,'De x Para DRE'!C:C,'De x Para DRE'!B:B),"")) -> 5110100801 | H54: DESPESA TÁXI E LOCOMOÇÕES FUNCIONÁRIOS | I54: =IF($G54="","",IFERROR(INDEX('De x Para DRE'!$E$3:$E$210,MATCH($G54,'De x Para DRE'!$B$3:$B$210,0)),"")) -> 3.1 G&A | J54: Locomoção | K54: 64.485 | L54: 64.485 | M54: 64.485 | N54: 64.485 | O54: 64.485 | P54: 64.485 | Q54: 64.485 | R54: 64.485 | S54: 64.485 | T54: 64.485 | U54: 64.485 | V54: 64.485 | W54: =SUM(K54:V54) -> 773.82 | Y54: =126.92+479.19 -> 606.11 | AD54: 0 | AE54: 192.96 | AF54: 0 | AG54: 0 | AH54: 0 | AI54: 0 | AJ54: =SUM(X54:AE54) -> 799.07 | AK54: =SUM(X54:AI54) -> 799.07 | AL54: 0 | AM54: 0 | AN54: 0 | AO54: 0 | AP54: 0 | AQ54: 0 | AR54: 0 | AS54: 0 | AT54: 0 | AU54: 0 | AV54: 0 | AW54: 0 | AX54: =IF(COUNT($AL54:$AW54)=0,"",SUM($AL54:$AW54)) -> 0 | AY54: =IF($AX54="","",$AX54-IF($W54="",0,$W54)) -> -773.82 | AZ54: =IF($AX54="","",$AX54-IF($AK54="",0,$AK54)) -> -799.07 | BB54: Rascunho
A55: =IF(OR($B55="",$D55="",$G55=""),"",ROW()-7) -> 48 | B55: ECEL COMERCIALIZADORA | C55: =IF($B55="","",IFERROR(INDEX(Apoio!$L$3:$L$81,MATCH($B55,Apoio!$K$3:$K$81,0)),"")) -> COMERCIALIZADORA | D55: C104 | E55: =IF($D55="","",IFERROR(INDEX(Apoio!$C$3:$C$81,MATCH($D55,Apoio!$B$3:$B$81,0)),"")) -> TI | F55: =IF($D55="","",IFERROR(INDEX(Apoio!$D$3:$D$81,MATCH($D55,Apoio!$B$3:$B$81,0)),"")) -> Marcelo Bronzatti | G55: =IF($H55="","",IFERROR(_xlfn.XLOOKUP(H55,'De x Para DRE'!C:C,'De x Para DRE'!B:B),"")) -> 5110100702 | H55: SISTEMAS DE GESTÃO ADM/OPERACIONAL | I55: =IF($G55="","",IFERROR(INDEX('De x Para DRE'!$E$3:$E$210,MATCH($G55,'De x Para DRE'!$B$3:$B$210,0)),"")) -> 3.1 G&A | J55: Computação na Nuvem (Amazon AWS) | K55: 8500 | L55: 8500 | M55: 8500 | N55: 8500 | O55: 8500 | P55: 8500 | Q55: 8500 | R55: 8500 | S55: 8500 | T55: 8500 | U55: 8500 | V55: 8500 | W55: =SUM(K55:V55) -> 102000 | X55: 5357.78 | Y55: 5850.93 | Z55: 10800 | AA55: 1934.43 | AB55: 1761.35 | AC55: =1666.97-98 -> 1568.97 | AD55: 1568.97 | AE55: =1666.97-AE52 -> 1568.97 | AF55: 1568.97 | AG55: 1568.97 | AH55: 1568.97 | AI55: 1568.97 | AJ55: =SUM(X55:AE55) -> 30411.4 | AK55: =SUM(X55:AI55) -> 36687.28 | AL55: 6000 | AM55: 6000 | AN55: 6000 | AO55: 6000 | AP55: 6000 | AQ55: 6000 | AR55: 6000 | AS55: 6000 | AT55: 6000 | AU55: 6000 | AV55: 6000 | AW55: 6000 | AX55: =IF(COUNT($AL55:$AW55)=0,"",SUM($AL55:$AW55)) -> 72000 | AY55: =IF($AX55="","",$AX55-IF($W55="",0,$W55)) -> -30000 | AZ55: =IF($AX55="","",$AX55-IF($AK55="",0,$AK55)) -> 35312.72 | BA55: CRESCIMENTO DE RECURSOS PARA HOSPEDAGEM DE APLICAÇÕES/DASHBOARDS/BOLETADOR e demais ferramentas internas para substituição como Teamguide, Boletador, Hub, Substituição Topdesk. | BB55: Rascunho
A56: =IF(OR($B56="",$D56="",$G56=""),"",ROW()-7) -> 49 | B56: ECEL COMERCIALIZADORA | C56: =IF($B56="","",IFERROR(INDEX(Apoio!$L$3:$L$81,MATCH($B56,Apoio!$K$3:$K$81,0)),"")) -> COMERCIALIZADORA | D56: C202 | E56: =IF($D56="","",IFERROR(INDEX(Apoio!$C$3:$C$81,MATCH($D56,Apoio!$B$3:$B$81,0)),"")) -> Middle Office | F56: =IF($D56="","",IFERROR(INDEX(Apoio!$D$3:$D$81,MATCH($D56,Apoio!$B$3:$B$81,0)),"")) -> Rafael Lemos | G56: =IF($H56="","",IFERROR(_xlfn.XLOOKUP(H56,'De x Para DRE'!C:C,'De x Para DRE'!B:B),"")) -> 5110100702 | H56: SISTEMAS DE GESTÃO ADM/OPERACIONAL | I56: =IF($G56="","",IFERROR(INDEX('De x Para DRE'!$E$3:$E$210,MATCH($G56,'De x Para DRE'!$B$3:$B$210,0)),"")) -> 3.1 G&A | J56: Licenças Newave e Decomp | M56: 60000 | W56: =SUM(K56:V56) -> 60000 | AD56: 0 | AE56: 0 | AF56: 0 | AG56: 0 | AH56: 0 | AI56: 0 | AJ56: =SUM(X56:AE56) -> 0 | AK56: =SUM(X56:AI56) -> 0 | AL56: 0 | AM56: 0 | AN56: 0 | AO56: 0 | AP56: 0 | AQ56: 0 | AR56: 0 | AS56: 0 | AT56: 0 | AU56: 0 | AV56: 0 | AW56: 0 | AX56: =IF(COUNT($AL56:$AW56)=0,"",SUM($AL56:$AW56)) -> 0 | AY56: =IF($AX56="","",$AX56-IF($W56="",0,$W56)) -> -60000 | AZ56: =IF($AX56="","",$AX56-IF($AK56="",0,$AK56)) -> 0 | BB56: Rascunho
A57: NOVOS OU FALTANTES
A58: =IF(OR($B58="",$D58="",$G58=""),"",ROW()-7) -> 51 | B58: ECEL COMERCIALIZADORA | C58: =IF($B58="","",IFERROR(INDEX(Apoio!$L$3:$L$81,MATCH($B58,Apoio!$K$3:$K$81,0)),"")) -> COMERCIALIZADORA | D58: C202 | E58: =IF($D58="","",IFERROR(INDEX(Apoio!$C$3:$C$81,MATCH($D58,Apoio!$B$3:$B$81,0)),"")) -> Middle Office | F58: =IF($D58="","",IFERROR(INDEX(Apoio!$D$3:$D$81,MATCH($D58,Apoio!$B$3:$B$81,0)),"")) -> Rafael Lemos | G58: =IF($H58="","",IFERROR(_xlfn.XLOOKUP(H58,'De x Para DRE'!C:C,'De x Para DRE'!B:B),"")) -> 5110100406 | H58: SERVIÇOS TÉCNICOS | I58: =IF($G58="","",IFERROR(INDEX('De x Para DRE'!$E$3:$E$210,MATCH($G58,'De x Para DRE'!$B$3:$B$210,0)),"")) -> 3.1 G&A | J58: Google Workspace de Risco (1 conta) | K58: 100 | L58: 100 | M58: 100 | N58: 100 | O58: 100 | P58: 100 | Q58: 100 | R58: 100 | S58: 100 | T58: 100 | U58: 100 | V58: 100 | X58: 98 | Y58: 98 | AC58: 98 | AD58: 98 | AE58: 98 | AF58: 98 | AG58: 98 | AH58: 98 | AI58: 98 | AJ58: =SUM(X58:AE58) -> 490 | AL58: 100 | AM58: 100 | AN58: 100 | AO58: 100 | AP58: 100 | AQ58: 100 | AR58: 100 | AS58: 100 | AT58: 100 | AU58: 100 | AV58: 100 | AW58: 100 | AX58: =IF(COUNT($AL58:$AW58)=0,"",SUM($AL58:$AW58)) -> 1200 | AY58: =IF($AX58="","",$AX58-IF($AK58="",0,$AK58)) -> 1200 | AZ58: =IF($AX58="","",$AX58-IF($AK58="",0,$AK58)) -> 1200 | BB58: Rascunho
A59: =IF(OR($B59="",$D59="",$G59=""),"",ROW()-7) -> 52 | B59: ECEL COMERCIALIZADORA | C59: =IF($B59="","",IFERROR(INDEX(Apoio!$L$3:$L$81,MATCH($B59,Apoio!$K$3:$K$81,0)),"")) -> COMERCIALIZADORA | D59: C104 | E59: =IF($D59="","",IFERROR(INDEX(Apoio!$C$3:$C$81,MATCH($D59,Apoio!$B$3:$B$81,0)),"")) -> TI | F59: =IF($D59="","",IFERROR(INDEX(Apoio!$D$3:$D$81,MATCH($D59,Apoio!$B$3:$B$81,0)),"")) -> Marcelo Bronzatti | G59: =IF($H59="","",IFERROR(_xlfn.XLOOKUP(H59,'De x Para DRE'!C:C,'De x Para DRE'!B:B),"")) -> 5110100201 | H59: MANUTENÇÃO DE MÁQ. EQUIP. E INSTALAÇÕES-PJ | I59: =IF($G59="","",IFERROR(INDEX('De x Para DRE'!$E$3:$E$210,MATCH($G59,'De x Para DRE'!$B$3:$B$210,0)),"")) -> 3.1 G&A | J59: CERTIPE - CERTIFICADO DIGITAL | K59: 333.33333 | L59: 333.33333 | M59: 333.33333 | N59: 333.33333 | O59: 333.33333 | P59: 333.33333 | Q59: 333.33333 | R59: 333.33333 | S59: 333.33333 | T59: 333.33333 | U59: 333.33333 | V59: 333.33333 | X59: 500 | Y59: =1059.6+400+819.5 -> 2279.1 | Z59: 957.2 | AC59: 233.92 | AD59: 0 | AE59: 233.92 | AF59: 333.33333 | AG59: 333.33333 | AH59: 333.33333 | AI59: 333.33333 | AJ59: =SUM(X59:AE59) -> 4204.14 | AL59: 0 | AM59: 0 | AN59: 0 | AO59: 0 | AP59: 0 | AQ59: 0 | AR59: 400 | AS59: 0 | AT59: 0 | AU59: 0 | AV59: 0 | AW59: 0 | AX59: =IF(COUNT($AL59:$AW59)=0,"",SUM($AL59:$AW59)) -> 400 | AY59: =IF($AX59="","",$AX59-IF($AK59="",0,$AK59)) -> 400 | AZ59: =IF($AX59="","",$AX59-IF($AK59="",0,$AK59)) -> 400 | BB59: Rascunho
A60: =IF(OR($B60="",$D60="",$G60=""),"",ROW()-7) -> 53 | B60: ECEL COMERCIALIZADORA | C60: =IF($B60="","",IFERROR(INDEX(Apoio!$L$3:$L$81,MATCH($B60,Apoio!$K$3:$K$81,0)),"")) -> COMERCIALIZADORA | D60: C104 | E60: =IF($D60="","",IFERROR(INDEX(Apoio!$C$3:$C$81,MATCH($D60,Apoio!$B$3:$B$81,0)),"")) -> TI | F60: =IF($D60="","",IFERROR(INDEX(Apoio!$D$3:$D$81,MATCH($D60,Apoio!$B$3:$B$81,0)),"")) -> Marcelo Bronzatti | G60: =IF($H60="","",IFERROR(_xlfn.XLOOKUP(H60,'De x Para DRE'!C:C,'De x Para DRE'!B:B),"")) -> 5110100702 | H60: SISTEMAS DE GESTÃO ADM/OPERACIONAL | I60: =IF($G60="","",IFERROR(INDEX('De x Para DRE'!$E$3:$E$210,MATCH($G60,'De x Para DRE'!$B$3:$B$210,0)),"")) -> 3.1 G&A | J60: RENOVAÇÃO SUPORTE TSPLUS (ACESSO REMOTO USINAS) | K60: 4232 | L60: 4232 | M60: 4232 | N60: =4232+5894 -> 10126 | O60: =4232+5894 -> 10126 | P60: =4232+5894 -> 10126 | Q60: =4443.6+5894 -> 10337.6 | R60: =4443.6+5894 -> 10337.6 | S60: =4443.6+5894 -> 10337.6 | T60: =4443.6+5894 -> 10337.6 | U60: =4443.6+5894 -> 10337.6 | V60: =4443.6+5894 -> 10337.6 | W60: 0 | X60: 0 | Y60: 8464.42 | Z60: 0 | AA60: 10706.3 | AB60: =3785.4+2688.69+4232.21 -> 10706.3 | AC60: =2688.69+3785.4+2688.69+3785.4+4232.21 -> 17180.39 | AD60: 10706.3 | AE60: 10706.3 | AF60: 10706.3 | AG60: 10706.3 | AH60: 10706.3 | AI60: 10706.3 | AJ60: =SUM(X60:AE60) -> 68470.01 | AL60: 0 | AM60: 0 | AN60: 0 | AO60: 0 | AP60: 0 | AQ60: 0 | AR60: 1000 | AS60: 0 | AT60: 0 | AU60: 0 | AV60: 0 | AW60: 0 | AX60: =IF(COUNT($AL60:$AW60)=0,"",SUM($AL60:$AW60)) -> 1000 | AY60: =IF($AX60="","",$AX60-IF($AK60="",0,$AK60)) -> 1000 | AZ60: =IF($AX60="","",$AX60-IF($AK60="",0,$AK60)) -> 1000 | BB60: Rascunho
A61: =IF(OR($B61="",$D61="",$G61=""),"",ROW()-7) -> 54 | B61: ECEL COMERCIALIZADORA | C61: =IF($B61="","",IFERROR(INDEX(Apoio!$L$3:$L$81,MATCH($B61,Apoio!$K$3:$K$81,0)),"")) -> COMERCIALIZADORA | D61: C104 | E61: =IF($D61="","",IFERROR(INDEX(Apoio!$C$3:$C$81,MATCH($D61,Apoio!$B$3:$B$81,0)),"")) -> TI | F61: =IF($D61="","",IFERROR(INDEX(Apoio!$D$3:$D$81,MATCH($D61,Apoio!$B$3:$B$81,0)),"")) -> Marcelo Bronzatti | G61: =IF($H61="","",IFERROR(_xlfn.XLOOKUP(H61,'De x Para DRE'!C:C,'De x Para DRE'!B:B),"")) -> 5110100501 | H61: DESPESA ASSESSORIA -PJ | I61: =IF($G61="","",IFERROR(INDEX('De x Para DRE'!$E$3:$E$210,MATCH($G61,'De x Para DRE'!$B$3:$B$210,0)),"")) -> 3.1 G&A | J61: Consultoria/treinamento Segurança Informação | K61: 4232 | L61: 4232 | M61: 4232 | N61: =4232+5894 -> 10126 | O61: =4232+5894 -> 10126 | P61: =4232+5894 -> 10126 | Q61: =4443.6+5894 -> 10337.6 | R61: =4443.6+5894 -> 10337.6 | S61: =4443.6+5894 -> 10337.6 | T61: =4443.6+5894 -> 10337.6 | U61: =4443.6+5894 -> 10337.6 | V61: =4443.6+5894 -> 10337.6 | W61: 0 | X61: 0 | Y61: 8464.42 | Z61: 0 | AA61: 10706.3 | AB61: =3785.4+2688.69+4232.21 -> 10706.3 | AC61: =2688.69+3785.4+2688.69+3785.4+4232.21 -> 17180.39 | AD61: 10706.3 | AE61: 10706.3 | AF61: 10706.3 | AG61: 10706.3 | AH61: 10706.3 | AI61: 10706.3 | AJ61: =SUM(X61:AE61) -> 68470.01 | AL61: 3500 | AM61: 3500 | AN61: 3500 | AO61: 3500 | AP61: 3500 | AQ61: 3500 | AR61: 3500 | AS61: 3500 | AT61: 3500 | AU61: 3500 | AV61: 3500 | AW61: 3500 | AX61: =IF(COUNT($AL61:$AW61)=0,"",SUM($AL61:$AW61)) -> 42000 | AY61: =IF($AX61="","",$AX61-IF($AK61="",0,$AK61)) -> 42000 | AZ61: =IF($AX61="","",$AX61-IF($AK61="",0,$AK61)) -> 42000 | BA61: Com a internalização de alguns softwares, se faz necessário consultoria de segurança para análise de vulnerabilidades. | BB61: Rascunho
A62: =IF(OR($B62="",$D62="",$G62=""),"",ROW()-7) -> 55 | B62: ECEL COMERCIALIZADORA | C62: =IF($B62="","",IFERROR(INDEX(Apoio!$L$3:$L$81,MATCH($B62,Apoio!$K$3:$K$81,0)),"")) -> COMERCIALIZADORA | D62: C104 | E62: =IF($D62="","",IFERROR(INDEX(Apoio!$C$3:$C$81,MATCH($D62,Apoio!$B$3:$B$81,0)),"")) -> TI | F62: =IF($D62="","",IFERROR(INDEX(Apoio!$D$3:$D$81,MATCH($D62,Apoio!$B$3:$B$81,0)),"")) -> Marcelo Bronzatti | G62: =IF($H62="","",IFERROR(_xlfn.XLOOKUP(H62,'De x Para DRE'!C:C,'De x Para DRE'!B:B),"")) -> 5110100501 | H62: DESPESA ASSESSORIA -PJ | I62: =IF($G62="","",IFERROR(INDEX('De x Para DRE'!$E$3:$E$210,MATCH($G62,'De x Para DRE'!$B$3:$B$210,0)),"")) -> 3.1 G&A | J62: Consultoria/treinamento Interligencia Artificial | K62: 4232 | L62: 4232 | M62: 4232 | N62: =4232+5894 -> 10126 | O62: =4232+5894 -> 10126 | P62: =4232+5894 -> 10126 | Q62: =4443.6+5894 -> 10337.6 | R62: =4443.6+5894 -> 10337.6 | S62: =4443.6+5894 -> 10337.6 | T62: =4443.6+5894 -> 10337.6 | U62: =4443.6+5894 -> 10337.6 | V62: =4443.6+5894 -> 10337.6 | W62: 0 | X62: 0 | Y62: 8464.42 | Z62: 0 | AA62: 10706.3 | AB62: =3785.4+2688.69+4232.21 -> 10706.3 | AC62: =2688.69+3785.4+2688.69+3785.4+4232.21 -> 17180.39 | AD62: 10706.3 | AE62: 10706.3 | AF62: 10706.3 | AG62: 10706.3 | AH62: 10706.3 | AI62: 10706.3 | AJ62: =SUM(X62:AE62) -> 68470.01 | AL62: 2000 | AM62: 2000 | AN62: 2000 | AO62: 2000 | AP62: 2000 | AQ62: 2000 | AR62: 2000 | AS62: 2000 | AT62: 2000 | AU62: 2000 | AV62: 2000 | AW62: 2000 | AX62: =IF(COUNT($AL62:$AW62)=0,"",SUM($AL62:$AW62)) -> 24000 | AY62: =IF($AX62="","",$AX62-IF($AK62="",0,$AK62)) -> 24000 | AZ62: =IF($AX62="","",$AX62-IF($AK62="",0,$AK62)) -> 24000 | BA62: Desenvolvimento & Inovação com utilização de IA . Consultoria e treinamento necessário com o crescimento interno do que chamamos de ShadowIT
A63: =IF(OR($B63="",$D63="",$G63=""),"",ROW()-7) -> 56 | B63: ECEL COMERCIALIZADORA | C63: =IF($B63="","",IFERROR(INDEX(Apoio!$L$3:$L$81,MATCH($B63,Apoio!$K$3:$K$81,0)),"")) -> COMERCIALIZADORA | D63: C104 | E63: =IF($D63="","",IFERROR(INDEX(Apoio!$C$3:$C$81,MATCH($D63,Apoio!$B$3:$B$81,0)),"")) -> TI | F63: =IF($D63="","",IFERROR(INDEX(Apoio!$D$3:$D$81,MATCH($D63,Apoio!$B$3:$B$81,0)),"")) -> Marcelo Bronzatti | G63: =IF($H63="","",IFERROR(_xlfn.XLOOKUP(H63,'De x Para DRE'!C:C,'De x Para DRE'!B:B),"")) -> 5110100501 | H63: DESPESA ASSESSORIA -PJ | I63: =IF($G63="","",IFERROR(INDEX('De x Para DRE'!$E$3:$E$210,MATCH($G63,'De x Para DRE'!$B$3:$B$210,0)),"")) -> 3.1 G&A | J63: Consultoria para apoio em Desenvolvimento | K63: 4232 | L63: 4232 | M63: 4232 | N63: =4232+5894 -> 10126 | O63: =4232+5894 -> 10126 | P63: =4232+5894 -> 10126 | Q63: =4443.6+5894 -> 10337.6 | R63: =4443.6+5894 -> 10337.6 | S63: =4443.6+5894 -> 10337.6 | T63: =4443.6+5894 -> 10337.6 | U63: =4443.6+5894 -> 10337.6 | V63: =4443.6+5894 -> 10337.6 | W63: 0 | X63: 0 | Y63: 8464.42 | Z63: 0 | AA63: 10706.3 | AB63: =3785.4+2688.69+4232.21 -> 10706.3 | AC63: =2688.69+3785.4+2688.69+3785.4+4232.21 -> 17180.39 | AD63: 10706.3 | AE63: 10706.3 | AF63: 10706.3 | AG63: 10706.3 | AH63: 10706.3 | AI63: 10706.3 | AJ63: =SUM(X63:AE63) -> 68470.01 | AL63: 20000 | AM63: 20000 | AN63: 20000 | AO63: 20000 | AP63: 20000 | AQ63: 20000 | AR63: 20000 | AS63: 20000 | AT63: 20000 | AU63: 20000 | AV63: 20000 | AW63: 20000 | AX63: =IF(COUNT($AL63:$AW63)=0,"",SUM($AL63:$AW63)) -> 240000 | AY63: =IF($AX63="","",$AX63-IF($AK63="",0,$AK63)) -> 240000 | AZ63: =IF($AX63="","",$AX63-IF($AK63="",0,$AK63)) -> 240000 | BA63: Estimativa de consultoria para apoio em desenvolvimento de softwares dado a internalização e crescimento da inovação . Base de 2 headcounts de 10k (Analista desenvolvedor Pleno)
A64: =IF(OR($B64="",$D64="",$G64=""),"",ROW()-7) -> 57 | B64: ECEL COMERCIALIZADORA | C64: =IF($B64="","",IFERROR(INDEX(Apoio!$L$3:$L$81,MATCH($B64,Apoio!$K$3:$K$81,0)),"")) -> COMERCIALIZADORA | D64: C104 | E64: =IF($D64="","",IFERROR(INDEX(Apoio!$C$3:$C$81,MATCH($D64,Apoio!$B$3:$B$81,0)),"")) -> TI | F64: =IF($D64="","",IFERROR(INDEX(Apoio!$D$3:$D$81,MATCH($D64,Apoio!$B$3:$B$81,0)),"")) -> Marcelo Bronzatti | G64: =IF($H64="","",IFERROR(_xlfn.XLOOKUP(H64,'De x Para DRE'!C:C,'De x Para DRE'!B:B),"")) -> 5110100201 | H64: MANUTENÇÃO DE MÁQ. EQUIP. E INSTALAÇÕES-PJ | I64: =IF($G64="","",IFERROR(INDEX('De x Para DRE'!$E$3:$E$210,MATCH($G64,'De x Para DRE'!$B$3:$B$210,0)),"")) -> 3.1 G&A | J64: Manutenção de Nobreaks e outros | K64: 333.33333 | L64: 333.33333 | M64: 333.33333 | N64: 333.33333 | O64: 333.33333 | P64: 333.33333 | Q64: 333.33333 | R64: 333.33333 | S64: 333.33333 | T64: 333.33333 | U64: 333.33333 | V64: 333.33333 | X64: 500 | Y64: =1059.6+400+819.5 -> 2279.1 | Z64: 957.2 | AC64: 233.92 | AD64: 0 | AE64: 233.92 | AF64: 333.33333 | AG64: 333.33333 | AH64: 333.33333 | AI64: 333.33333 | AJ64: =SUM(X64:AE64) -> 4204.14 | AQ64: 10000 | AW64: 10000 | AX64: =IF(COUNT($AL64:$AW64)=0,"",SUM($AL64:$AW64)) -> 20000 | AY64: =IF($AX64="","",$AX64-IF($AK64="",0,$AK64)) -> 20000 | AZ64: =IF($AX64="","",$AX64-IF($AK64="",0,$AK64)) -> 20000 | BB64: Rascunho
A65: =IF(OR($B65="",$D65="",$G65=""),"",ROW()-7) -> 58 | B65: ECEL COMERCIALIZADORA | C65: =IF($B65="","",IFERROR(INDEX(Apoio!$L$3:$L$81,MATCH($B65,Apoio!$K$3:$K$81,0)),"")) -> COMERCIALIZADORA | D65: C104 | E65: =IF($D65="","",IFERROR(INDEX(Apoio!$C$3:$C$81,MATCH($D65,Apoio!$B$3:$B$81,0)),"")) -> TI | F65: =IF($D65="","",IFERROR(INDEX(Apoio!$D$3:$D$81,MATCH($D65,Apoio!$B$3:$B$81,0)),"")) -> Marcelo Bronzatti | G65: =IF($H65="","",IFERROR(_xlfn.XLOOKUP(H65,'De x Para DRE'!C:C,'De x Para DRE'!B:B),"")) -> 5110100707 | H65: DESPESA MANUTENÇÃO DE HARDWARE/SOFTWARE | I65: =IF($G65="","",IFERROR(INDEX('De x Para DRE'!$E$3:$E$210,MATCH($G65,'De x Para DRE'!$B$3:$B$210,0)),"")) -> 3.1 G&A | J65: Peças de reposição (Periféricos em Geral) | K65: 333.33333 | L65: 333.33333 | M65: 333.33333 | N65: 333.33333 | O65: 333.33333 | P65: 333.33333 | Q65: 333.33333 | R65: 333.33333 | S65: 333.33333 | T65: 333.33333 | U65: 333.33333 | V65: 333.33333 | X65: 500 | Y65: =1059.6+400+819.5 -> 2279.1 | Z65: 957.2 | AC65: 233.92 | AD65: 0 | AE65: 233.92 | AF65: 333.33333 | AG65: 333.33333 | AH65: 333.33333 | AI65: 333.33333 | AJ65: =SUM(X65:AE65) -> 4204.14 | AL65: 2500 | AM65: 2500 | AN65: 2500 | AO65: 2500 | AP65: 2500 | AQ65: 2500 | AR65: 2500 | AS65: 2500 | AT65: 2500 | AU65: 2500 | AV65: 2500 | AW65: 2500 | AX65: =IF(COUNT($AL65:$AW65)=0,"",SUM($AL65:$AW65)) -> 30000 | AY65: =IF($AX65="","",$AX65-IF($AK65="",0,$AK65)) -> 30000 | AZ65: =IF($AX65="","",$AX65-IF($AK65="",0,$AK65)) -> 30000 | BB65: Rascunho
A66: =IF(OR($B66="",$D66="",$G66=""),"",ROW()-7) -> 59 | B66: ECEL COMERCIALIZADORA | C66: =IF($B66="","",IFERROR(INDEX(Apoio!$L$3:$L$81,MATCH($B66,Apoio!$K$3:$K$81,0)),"")) -> COMERCIALIZADORA | D66: C104 | E66: =IF($D66="","",IFERROR(INDEX(Apoio!$C$3:$C$81,MATCH($D66,Apoio!$B$3:$B$81,0)),"")) -> TI | F66: =IF($D66="","",IFERROR(INDEX(Apoio!$D$3:$D$81,MATCH($D66,Apoio!$B$3:$B$81,0)),"")) -> Marcelo Bronzatti | G66: =IF($H66="","",IFERROR(_xlfn.XLOOKUP(H66,'De x Para DRE'!C:C,'De x Para DRE'!B:B),"")) -> 5110100702 | H66: SISTEMAS DE GESTÃO ADM/OPERACIONAL | I66: =IF($G66="","",IFERROR(INDEX('De x Para DRE'!$E$3:$E$210,MATCH($G66,'De x Para DRE'!$B$3:$B$210,0)),"")) -> 3.1 G&A | J66: BREVO (Mensageria) | K66: 4232 | L66: 4232 | M66: 4232 | N66: =4232+5894 -> 10126 | O66: =4232+5894 -> 10126 | P66: =4232+5894 -> 10126 | Q66: =4443.6+5894 -> 10337.6 | R66: =4443.6+5894 -> 10337.6 | S66: =4443.6+5894 -> 10337.6 | T66: =4443.6+5894 -> 10337.6 | U66: =4443.6+5894 -> 10337.6 | V66: =4443.6+5894 -> 10337.6 | X66: 0 | Y66: 8464.42 | Z66: 0 | AA66: 10706.3 | AB66: =3785.4+2688.69+4232.21 -> 10706.3 | AC66: =2688.69+3785.4+2688.69+3785.4+4232.21 -> 17180.39 | AD66: 10706.3 | AE66: 10706.3 | AF66: 10706.3 | AG66: 10706.3 | AH66: 10706.3 | AI66: 10706.3 | AJ66: =SUM(X66:AE66) -> 68470.01 | AL66: 500 | AM66: 500 | AN66: 500 | AO66: 500 | AP66: 500 | AQ66: 500 | AR66: 500 | AS66: 500 | AT66: 500 | AU66: 500 | AV66: 500 | AW66: 500 | AX66: =IF(COUNT($AL66:$AW66)=0,"",SUM($AL66:$AW66)) -> 6000 | AY66: =IF($AX66="","",$AX66-IF($AK66="",0,$AK66)) -> 6000 | AZ66: =IF($AX66="","",$AX66-IF($AK66="",0,$AK66)) -> 6000 | BB66: Rascunho
A67: =IF(OR($B67="",$D67="",$G67=""),"",ROW()-7) -> 60 | B67: ECEL COMERCIALIZADORA | C67: =IF($B67="","",IFERROR(INDEX(Apoio!$L$3:$L$81,MATCH($B67,Apoio!$K$3:$K$81,0)),"")) -> COMERCIALIZADORA | D67: C104 | E67: =IF($D67="","",IFERROR(INDEX(Apoio!$C$3:$C$81,MATCH($D67,Apoio!$B$3:$B$81,0)),"")) -> TI | F67: =IF($D67="","",IFERROR(INDEX(Apoio!$D$3:$D$81,MATCH($D67,Apoio!$B$3:$B$81,0)),"")) -> Marcelo Bronzatti | G67: =IF($H67="","",IFERROR(_xlfn.XLOOKUP(H67,'De x Para DRE'!C:C,'De x Para DRE'!B:B),"")) -> 5110100702 | H67: SISTEMAS DE GESTÃO ADM/OPERACIONAL | I67: =IF($G67="","",IFERROR(INDEX('De x Para DRE'!$E$3:$E$210,MATCH($G67,'De x Para DRE'!$B$3:$B$210,0)),"")) -> 3.1 G&A | J67: SISTEMA ISO (SOGI) - AMBIPAR | K67: 4232 | L67: 4232 | M67: 4232 | N67: =4232+5894 -> 10126 | O67: =4232+5894 -> 10126 | P67: =4232+5894 -> 10126 | Q67: =4443.6+5894 -> 10337.6 | R67: =4443.6+5894 -> 10337.6 | S67: =4443.6+5894 -> 10337.6 | T67: =4443.6+5894 -> 10337.6 | U67: =4443.6+5894 -> 10337.6 | V67: =4443.6+5894 -> 10337.6 | X67: 0 | Y67: 8464.42 | Z67: 0 | AA67: 10706.3 | AB67: =3785.4+2688.69+4232.21 -> 10706.3 | AC67: =2688.69+3785.4+2688.69+3785.4+4232.21 -> 17180.39 | AD67: 10706.3 | AE67: 10706.3 | AF67: 10706.3 | AG67: 10706.3 | AH67: 10706.3 | AI67: 10706.3 | AJ67: =SUM(X67:AE67) -> 68470.01 | AL67: 450 | AM67: 450 | AN67: 450 | AO67: 450 | AP67: 450 | AQ67: 450 | AR67: 450 | AS67: 450 | AT67: 450 | AU67: 450 | AV67: 450 | AW67: 450 | AX67: =IF(COUNT($AL67:$AW67)=0,"",SUM($AL67:$AW67)) -> 5400 | AY67: =IF($AX67="","",$AX67-IF($AK67="",0,$AK67)) -> 5400 | AZ67: =IF($AX67="","",$AX67-IF($AK67="",0,$AK67)) -> 5400 | BB67: Rascunho
A68: =IF(OR($B68="",$D68="",$G68=""),"",ROW()-7) -> 61 | B68: ECEL COMERCIALIZADORA | C68: =IF($B68="","",IFERROR(INDEX(Apoio!$L$3:$L$81,MATCH($B68,Apoio!$K$3:$K$81,0)),"")) -> COMERCIALIZADORA | D68: C104 | E68: =IF($D68="","",IFERROR(INDEX(Apoio!$C$3:$C$81,MATCH($D68,Apoio!$B$3:$B$81,0)),"")) -> TI | F68: =IF($D68="","",IFERROR(INDEX(Apoio!$D$3:$D$81,MATCH($D68,Apoio!$B$3:$B$81,0)),"")) -> Marcelo Bronzatti | G68: =IF($H68="","",IFERROR(_xlfn.XLOOKUP(H68,'De x Para DRE'!C:C,'De x Para DRE'!B:B),"")) -> 5110100702 | H68: SISTEMAS DE GESTÃO ADM/OPERACIONAL | I68: =IF($G68="","",IFERROR(INDEX('De x Para DRE'!$E$3:$E$210,MATCH($G68,'De x Para DRE'!$B$3:$B$210,0)),"")) -> 3.1 G&A | J68: GRAVITYZONE - Bitdefender | K68: 4232 | L68: 4232 | M68: 4232 | N68: =4232+5894 -> 10126 | O68: =4232+5894 -> 10126 | P68: =4232+5894 -> 10126 | Q68: =4443.6+5894 -> 10337.6 | R68: =4443.6+5894 -> 10337.6 | S68: =4443.6+5894 -> 10337.6 | T68: =4443.6+5894 -> 10337.6 | U68: =4443.6+5894 -> 10337.6 | V68: =4443.6+5894 -> 10337.6 | X68: 0 | Y68: 8464.42 | Z68: 0 | AA68: 10706.3 | AB68: =3785.4+2688.69+4232.21 -> 10706.3 | AC68: =2688.69+3785.4+2688.69+3785.4+4232.21 -> 17180.39 | AD68: 10706.3 | AE68: 10706.3 | AF68: 10706.3 | AG68: 10706.3 | AH68: 10706.3 | AI68: 10706.3 | AJ68: =SUM(X68:AE68) -> 68470.01 | AL68: 13000 | AM68: 0 | AN68: 0 | AO68: 0 | AP68: 0 | AQ68: 0 | AR68: 0 | AS68: 0 | AT68: 0 | AU68: 0 | AV68: 0 | AW68: 0 | AX68: =IF(COUNT($AL68:$AW68)=0,"",SUM($AL68:$AW68)) -> 13000 | AY68: =IF($AX68="","",$AX68-IF($AK68="",0,$AK68)) -> 13000 | AZ68: =IF($AX68="","",$AX68-IF($AK68="",0,$AK68)) -> 13000 | BA68: Solução de antivirus em substituição do Kaspersky - Valores para 110 licencas (validade de 3 anos com 1 adicional gratuíto) | BB68: Rascunho

Sheet Contratos
A1: Fornecedor | B1: Número do contrato | C1: Breve descrição | D1: Dt início | E1: Dt final | F1: Dt canc | G1: Av Prévio | H1: Vlr atual | I1: Vigência | J1: Orçamento 2027 | K1: OBS | L1: PLANO | M1: Coluna1
A2: A2M TECNOLOGIA EM INTERNET LTDA (SURFIX) | B2: 20260608_SURFIX_VOIP | C2: TELEFONIA VOIP (15 LINHAS + PABX DIGITAL COM 4 CANAIS) | D2: 46181 | E2: 46912 | G2: n/a | H2: 664 | I2: 2 anos | J2: =Tabela1[[#This Row],[Vlr atual]]*1.0411 -> 691.2904
A3: ADOBE SYSTEMS SOFTWARE IRELAND LIMITED | B3: 20260804_ADOBE_D375115D9C47327EC90A | C3: ADOBE CLOUD CLOUD PRO / ADOBE STOCK - LICENCAS | D3: 46238 | E3: 46603 | H3: 1670 | I3: 1 ano | J3: =Tabela1[[#This Row],[Vlr atual]]*1.0411 -> 1738.637 | L3: REDUZIR PARA 2 LICENCAS
A4: ARPSIST SERVICOS DE ENGENHARIA LTDA | B4: 20260127_ARPSIST - CISCO -PP-2510-003-02 | C4: RENOVAÇÃO LICENÇAS CISCO MERAKI (3Y) + AQUISIÇÃO AP MR44 | D4: 46049 | E4: 47145 | H4: 31010.84 | I4: 3 anos | J4: =Tabela1[[#This Row],[Vlr atual]]*1.0411 -> 32285.386 | L4: REDUZIMOS PARA 1300 P/MES
A5: ARPSIST SERVICOS DE ENGENHARIA LTDA | B5: 20260511_ARPSIST_SUP.NETWORK 2026 | C5: 20260511_PP-2605-010ARPSIST_SUPORTE NETWORK 2026 | D5: 46153 | E5: 46517 | H5: 1560 | I5: 1 ano | J5: 1250 | L5: REDUZIR HRS E VLR MES
A6: CLICKSIGN GESTÃO DE DOCUMENTOS S/A | B6: 20250827_CLICKSIGN_42911791705 | C6: CONTRATO CLICKSIGN PLANO AVANCADO - 3600 DOC/ANO | D6: 28/08/20026 | E6: 46626 | G6: 30 dias | H6: 822.61 | I6: 1 ano | J6: =Tabela1[[#This Row],[Vlr atual]]*1.0411 -> 856.41927 | K6: REAJUSTE IGP/M | L6: SEM ALTERAÇÃO
A7: COLMEIA CONSULTORIA E REPRESENTAÇÃO COMERCIAL S/A. | C7: PLATAFORMA DE CHATBOT | D7: 45853 | E7: 46217 | G7: 60 dias | H7: 1370 | I7: 1 ano | J7: =Tabela1[[#This Row],[Vlr atual]]*1.0411 -> 1426.307 | K7: REAJUSTE IGP/M | L7: SEM ALTERAÇÃO | M7: ESTÁ ACIMA DEVIDO A FRANQUIA DE USO
A8: IMAGINE SOFTWARE LTDA - 4ERP | B8: 20260514_4ERPLITE/4EXP-JA-2026-081/082 | C8: JA-2026-081/082 LICENÇA DE USO 4ERP LITE E 4EXPENSES | D8: 46156 | E8: 46520 | H8: 1800 | I8: 1 ano | J8: =Tabela1[[#This Row],[Vlr atual]]*1.0411 -> 1873.98
A9: INTERNET SAT SERVIÇOS DE TELECOMUNICAÇÕES LTDA | B9: 20250521_INTERNETSAT-TELECOM UFV RIACHO | C9: INFRA DE TELECOM UFV RIACHO | D9: 45798 | E9: 47623 | H9: 10980 | J9: =Tabela1[[#This Row],[Vlr atual]]*1.0411 -> 11431.278
A10: MUNDIVOX CLOUD LTDA. | B10: 202410_MUNDIVOX_PE | C10: INTERNET DEDICADA 500GB PE | D10: 45566 | E10: 46691 | H10: 0 | I10: 2 anos | J10: =Tabela1[[#This Row],[Vlr atual]]*1.0411 -> 0
A11: MUNDIVOX CLOUD LTDA. | B11: 202603_MUNDIVOX_PE_2 (6371726759/26) | C11: INTERNET DEDICADA 150GB PE (UPGRADE LINK PRINCIPAL) | D11: 46095 | E11: 46825 | H11: 1241.48 | I11: 2 anos | J11: =Tabela1[[#This Row],[Vlr atual]]*1.0411 -> 1292.5048
A12: PARADIGMA BUSINESS SOLUTIONS LTDA | B12: PARADIGMA BUSINESS SOLUTIONS LTDA | C12: SOFTWARE WBC-ENERGY E SERVIÇOS DE SUSTENTAÇÃO/SUPORTE | D12: 45376 | E12: 46470 | F12: 46357 | G12: 90 dias | H12: 28008.13 | I12: 3 anos | J12: =36800*1.0411 -> 38312.48 | K12: REAJUSTE IGP/M E RETORNO DO VALOR ORIGINAL PÓS RENEGOCIAÇÃO | L12: MIGRAR BOLETADOR E AVISO PRÉVIO EM DEZEMBRO/26
A13: RAMO SISTEMAS DIGITAIS LTDA | B13: 20251229_RAMO - SAP/ADDONS/SUP PV-246 | C13: Aquis.Licenças, Addons e Suporte SAP B1 | D13: 46027 | E13: 46752 | G13: 30 dias | H13: 15251 | I13: 2 anos | J13: =Tabela1[[#This Row],[Vlr atual]]*1.0411 -> 15877.816 | K13: REAJUSTE IGP/M | L13: SEM ALTERAÇÃO
A14: RAMO SISTEMAS DIGITAIS LTDA | B14: 20260114_RAMO - PCTO 250 HORAS - P142601 | C14: PROPOSTA 142601 - CONTR.PACOTE 250 HORAS DESENV. | D14: 46036 | E14: 46401 | G14: 30 dias | H14: 40233.24 | I14: 1 ano | J14: =Tabela1[[#This Row],[Vlr atual]]*1.0411 -> 41886.826
A15: RAMO SISTEMAS DIGITAIS LTDA | B15: 20260327_RAMO - CS26109-CHATBOT&MIGRAÇÃO | C15: PROPOSTA CS26109 - CHATBOT & MIGRAÇÃO SAP ALFA -> RAMO (AUTOSKY) | D15: 46108 | E15: 46387 | H15: 19215.39 | I15: 1 ano | J15: =Tabela1[[#This Row],[Vlr atual]]*1.0411 -> 20005.143
A16: RAMO SISTEMAS DIGITAIS LTDA | B16: 20261011_RAMO - 28HS-INTEGR.DOMINIOXSAP | C16: PROPOSTA CS26320- CONTR.PACOTE 28 HR DESENV. INTEGRAÇÃO DOMINIO X SAP | D16: 46245 | E16: 46367 | H16: 4200 | J16: =Tabela1[[#This Row],[Vlr atual]]*1.0411 -> 4372.62
A17: SKY.ONE TECNOLOGIA EM SOFTWARE S.A | B17: 202405_2830354-SKYONE STUDIO-3 ANOS | C17: SKYONE - PLATAFORMA DE INTEGRAÇÃO DE DADOS SAPONE X PARADIGMA | D17: 45440 | E17: 46535 | H17: 4668.28 | I17: 3 anos | J17: =Tabela1[[#This Row],[Vlr atual]]*1.0411 -> 4860.1463
A18: SKY.ONE TECNOLOGIA EM SOFTWARE S.A | B18: 20260212_SKYONE_AUTOSKY_CLOUD SAPB1 RAMO | C18: CONTRATO DE HOSPEDAGEM CLOUD AUTOSKY SAP B1 - RAMO | D18: 46065 | E18: 47161 | G18: 90 dias | H18: 6474.09 | I18: 3 anos | J18: =Tabela1[[#This Row],[Vlr atual]]*1.0411 -> 6740.1751 | K18: MULTA 30% CANCELAMENTO | L18: ABRIR TICKET DE RENEGOCIAÇÃO
A19: SOU CLOUD SERVIÇOS GERENCIADOS EM NUVEM LTDA | B19: 20251001_SOUCLOUD SOU-OP-015901 | C19: SUBSCRIÇÃO ANUAL 2025/2026 - MICROSOFT (OFFICE 365 BUSINESS PREMIUM). | D19: 45931 | E19: 46295 | G19: 30 dias | H19: 21970.64 | I19: 1 ano | J19: =Tabela1[[#This Row],[Vlr atual]]*1.0411 -> 22873.633 | L19: MUDAR PARA MENSAL E OTIMIZAR LICENCAS
A20: TEAMGUIDE | C20: PLATAFORMA DE TEAM (CONTRATO COM MANU) | G20: 46295 | H20: 1100 | I20: 1 ano | J20: =Tabela1[[#This Row],[Vlr atual]]*1.0411 -> 1145.21 | L20: CANCELAR/CRIAR INTERNAMENTE | M20: PROJETO INTERNO
A21: TOPdesk Brasil | B21: 20250219_TOPDESK - QUO-260212-31428 | C21: 2o. ADIT.CONTRATO CESSÃO DE USO NA MODALIDADE SAAS TOPdesk Engaged | D21: 46082 | E21: 46477 | G21: 46419 | H21: 5014.46 | I21: 1 ano | J21: =Tabela1[[#This Row],[Vlr atual]]*1.0411 -> 5220.5543 | K21: MULTA 15% SALDO REMANESCENTE SE CANCELAR ANTES | L21: MIGRAR GLPI
A22: TSPLUS BRASIL CONSULTORIA EM TECNOLOGIA LTDA | B22: 20260702_TSPLUS_PROPOSTA10690 | C22: TSPLUS - LICENCA PERPÉTUA | D22: 46205 | E22: 72868 | H22: 2686.86 | J22: =Tabela1[[#This Row],[Vlr atual]]*1.0411 -> 2797.2899
A23: VIVO - TELEFONICA BRASIL S/A | B23: 20231016_VIVO_2875461_VVN (30 LINHAS) | C23: VIVO VOZ NEGOCIO - PROPOSTA 2875461 - 30 LINHAS | D23: 45217 | E23: 46313 | H23: 1900 | I23: 3 anos | J23: =Tabela1[[#This Row],[Vlr atual]]*1.0411 -> 1978.09 | L23: CANC SET/26 - SUBST POR SURFIX
A24: VIVO - TELEFONICA BRASIL S/A | B24: 20240301_VIVO_2948250_VVN (31 LINHAS) | C24: VIVO VOZ NEGOCIO - PROPOSTA 2948250 - 31 LINHAS | D24: 45352 | E24: 46447 | F24: ######### | H24: 930 | I24: 3 anos | J24: =Tabela1[[#This Row],[Vlr atual]]*1.0411 -> 968.223 | L24: CANC SET/26 - SUBST POR SURFIX
A25: VIVO - TELEFONICA BRASIL S/A | B25: 20260113_S000004780954_VIVO_MOVEL_PORT. | C25: VIVO MOVEL ILIMITADO SMART EMPRESAS 15GB (4 LINHAS) | D25: 46035 | E25: 46765 | H25: 195.96 | I25: 2 anos | J25: =Tabela1[[#This Row],[Vlr atual]]*1.0411 -> 204.01396
A26: VIVO - TELEFONICA BRASIL S/A | B26: 20260113_S000004790735_VIVO_MOVEL_PORT. | C26: VIVO MOVEL ILIMITADO SMART EMPRESAS 15GB (3 LINHAS) | D26: 46035 | E26: 46765 | H26: 146.97 | I26: 2 anos | J26: =Tabela1[[#This Row],[Vlr atual]]*1.0411 -> 153.01047
A27: VIVO - TELEFONICA BRASIL S/A | B27: 20260114_S000004807737_VIVO_MOVEL_PORT. | C27: VIVO MOVEL ILIMITADO SMART EMPRESAS 15GB (11 LINHAS) | D27: 46036 | E27: 46766 | H27: 538.89 | I27: 2 anos | J27: =Tabela1[[#This Row],[Vlr atual]]*1.0411 -> 561.03838
A28: VIVO - TELEFONICA BRASIL S/A | B28: 20260114_S000004807737_VIVO_MOVEL_PORT. | C28: VIVO MOVEL ILIMITADO SMART EMPRESAS 15GB (49 LINHAS) + TRADE-IN 100% DESC 3 MESES | D28: 46119 | E28: 46850 | H28: 2400.51 | I28: 2 anos | J28: =Tabela1[[#This Row],[Vlr atual]]*1.0411 -> 2499.171
A29: VIVO - TELEFONICA BRASIL S/A | B29: 20260810_S000006959453_VIVO_MOVEL_PORT. | C29: VIVO MOVEL ILIMITADO SMART EMPRESAS 15GB (1 LINHA) | D29: 46244 | E29: 46975 | H29: 48.99 | I29: 2 anos | J29: =Tabela1[[#This Row],[Vlr atual]]*1.0411 -> 51.003489
A30: YSSY SOLUÇÕES S/A | B30: 20231002_YSSY-YSOL23/04/19881 | C30: Licenças Webex e Umbrella | D30: 45201 | E30: 46297 | H30: 71786.33 | I30: 3 anos | J30: =Tabela1[[#This Row],[Vlr atual]]*1.0411 -> 74736.748 | L30: CANCELAR UMBRELLA MERAKI SIFI E FIREWALL FOI RENOVADO EM 2026 POR 3 ANOS
